kotlin version: 2.0.21
error message: org.jetbrains.kotlin.codegen.CompilationException: Back-end (JVM) Internal error: Couldn't transform method node:
importPreset (Ljava/lang/String;)Lcom/hieltech/haramblur/data/PresetImportResult;:
  @Lorg/jetbrains/annotations/NotNull;() // invisible
    // annotable parameter count: 1 (visible)
    // annotable parameter count: 1 (invisible)
    @Lorg/jetbrains/annotations/NotNull;() // invisible, parameter 0
    TRYCATCHBLOCK L0 L1 L2 java/lang/IllegalArgumentException
    TRYCATCHBLOCK L3 L4 L5 java/lang/IllegalArgumentException
    TRYCATCHBLOCK L6 L7 L8 java/lang/IllegalArgumentException
    TRYCATCHBLOCK L9 L10 L11 java/lang/IllegalArgumentException
    TRYCATCHBLOCK L12 L13 L14 java/lang/IllegalArgumentException
    TRYCATCHBLOCK L15 L16 L17 java/lang/IllegalArgumentException
    TRYCATCHBLOCK L18 L19 L20 java/lang/IllegalArgumentException
    TRYCATCHBLOCK L21 L22 L23 java/lang/Exception
    TRYCATCHBLOCK L24 L25 L26 java/lang/Exception
    TRYCATCHBLOCK L27 L28 L29 java/lang/Exception
   L30
    ALOAD 1
    LDC "presetJson"
    INVOKESTATIC kotlin/jvm/internal/Intrinsics.checkNotNullParameter (Ljava/lang/Object;Ljava/lang/String;)V
    ALOAD 1
    INVOKESTATIC kotlin/jvm/internal/$PseudoInsn.AS_NOT_NULL (Ljava/lang/Object;)Ljava/lang/Object;
    ASTORE 1
   L31
    LINENUMBER 459 L31
    ALOAD 0
    GETFIELD com/hieltech/haramblur/ui/SettingsViewModel.settingsRepository : Lcom/hieltech/haramblur/data/SettingsRepository;
    ALOAD 1
    INVOKEVIRTUAL com/hieltech/haramblur/data/SettingsRepository.validatePresetData (Ljava/lang/String;)Lcom/hieltech/haramblur/data/ValidationResult;
    ASTORE 2
   L32
    LINENUMBER 460 L32
    ALOAD 2
    INVOKEVIRTUAL com/hieltech/haramblur/data/ValidationResult.isValid ()Z
    IFNE L33
   L34
    LINENUMBER 461 L34
    NEW com/hieltech/haramblur/data/PresetImportResult$Error
    DUP
   L35
    LINENUMBER 462 L35
    ALOAD 2
    INVOKEVIRTUAL com/hieltech/haramblur/data/ValidationResult.getErrors ()Ljava/util/List;
    CHECKCAST java/lang/Iterable
    LDC "\n"
    CHECKCAST java/lang/CharSequence
    ACONST_NULL
    ACONST_NULL
    ICONST_0
    ACONST_NULL
    ACONST_NULL
    BIPUSH 62
    ACONST_NULL
    INVOKESTATIC kotlin/collections/CollectionsKt.joinToString$default (Ljava/lang/Iterable;Ljava/lang/CharSequence;Ljava/lang/CharSequence;Ljava/lang/CharSequence;ILjava/lang/CharSequence;Lkotlin/jvm/functions/Function1;ILjava/lang/Object;)Ljava/lang/String;
   L36
    LINENUMBER 463 L36
    GETSTATIC com/hieltech/haramblur/data/ImportErrorType.INVALID_JSON : Lcom/hieltech/haramblur/data/ImportErrorType;
   L37
    LINENUMBER 461 L37
    INVOKESPECIAL com/hieltech/haramblur/data/PresetImportResult$Error.<init> (Ljava/lang/String;Lcom/hieltech/haramblur/data/ImportErrorType;)V
    CHECKCAST com/hieltech/haramblur/data/PresetImportResult
    ARETURN
   L38
    NOP
   L33
    LINENUMBER 467 L33
   L39
   L27
    NOP
   L40
    LINENUMBER 468 L40
    NEW org/json/JSONObject
    DUP
    ALOAD 1
    INVOKESPECIAL org/json/JSONObject.<init> (Ljava/lang/String;)V
    ASTORE 3
   L41
    LINENUMBER 469 L41
    ALOAD 3
    LDC "settings"
    INVOKEVIRTUAL org/json/JSONObject.getJSONObject (Ljava/lang/String;)Lorg/json/JSONObject;
    ASTORE 4
   L42
    LINENUMBER 472 L42
    ALOAD 4
    LDC "enableFaceDetection"
    NOP
    ICONST_1
    INVOKEVIRTUAL org/json/JSONObject.optBoolean (Ljava/lang/String;Z)Z
    ISTORE 6
   L43
    LINENUMBER 473 L43
    ALOAD 4
    LDC "enableNSFWDetection"
    NOP
    ICONST_1
    INVOKEVIRTUAL org/json/JSONObject.optBoolean (Ljava/lang/String;Z)Z
    ISTORE 7
   L44
    LINENUMBER 474 L44
    ALOAD 4
    LDC "blurMaleFaces"
    NOP
    ICONST_0
    INVOKEVIRTUAL org/json/JSONObject.optBoolean (Ljava/lang/String;Z)Z
    ISTORE 8
   L45
    LINENUMBER 475 L45
    ALOAD 4
    LDC "blurFemaleFaces"
    NOP
    ICONST_1
    INVOKEVIRTUAL org/json/JSONObject.optBoolean (Ljava/lang/String;Z)Z
    ISTORE 9
   L46
    LINENUMBER 476 L46
    ALOAD 4
    LDC "detectionSensitivity"
    LDC 0.8
    INVOKEVIRTUAL org/json/JSONObject.optDouble (Ljava/lang/String;D)D
    D2F
    FSTORE 10
   L47
    LINENUMBER 477 L47
   L48
   L0
    NOP
   L49
    LINENUMBER 478 L49
    ALOAD 4
    LDC "blurIntensity"
    LDC "STRONG"
    INVOKEVIRTUAL org/json/JSONObject.optString (Ljava/lang/String;Ljava/lang/String;)Ljava/lang/String;
    ASTORE 12
   L50
    ALOAD 12
    LDC "optString(...)"
    INVOKESTATIC kotlin/jvm/internal/Intrinsics.checkNotNullExpressionValue (Ljava/lang/Object;Ljava/lang/String;)V
    ALOAD 12
    INVOKESTATIC kotlin/jvm/internal/$PseudoInsn.AS_NOT_NULL (Ljava/lang/Object;)Ljava/lang/Object;
    ASTORE 12
    ALOAD 12
   L51
    CHECKCAST java/lang/String
    INVOKESTATIC com/hieltech/haramblur/data/BlurIntensity.valueOf (Ljava/lang/String;)Lcom/hieltech/haramblur/data/BlurIntensity;
    ASTORE 12
   L1
    GOTO L52
   L2
    LINENUMBER 479 L2
    ASTORE 13
   L53
    GETSTATIC com/hieltech/haramblur/data/BlurIntensity.STRONG : Lcom/hieltech/haramblur/data/BlurIntensity;
    ASTORE 12
   L52
    LINENUMBER 477 L52
    ALOAD 12
    ASTORE 11
   L54
    LINENUMBER 480 L54
   L55
   L3
    NOP
   L56
    LINENUMBER 481 L56
    ALOAD 4
    LDC "blurStyle"
    LDC "ARTISTIC"
    INVOKEVIRTUAL org/json/JSONObject.optString (Ljava/lang/String;Ljava/lang/String;)Ljava/lang/String;
    ASTORE 13
   L57
    ALOAD 13
    LDC "optString(...)"
    INVOKESTATIC kotlin/jvm/internal/Intrinsics.checkNotNullExpressionValue (Ljava/lang/Object;Ljava/lang/String;)V
    ALOAD 13
    INVOKESTATIC kotlin/jvm/internal/$PseudoInsn.AS_NOT_NULL (Ljava/lang/Object;)Ljava/lang/Object;
    ASTORE 13
    ALOAD 13
   L58
    CHECKCAST java/lang/String
    INVOKESTATIC com/hieltech/haramblur/data/BlurStyle.valueOf (Ljava/lang/String;)Lcom/hieltech/haramblur/data/BlurStyle;
    ASTORE 13
   L4
    GOTO L59
   L5
    LINENUMBER 482 L5
    ASTORE 14
   L60
    GETSTATIC com/hieltech/haramblur/data/BlurStyle.ARTISTIC : Lcom/hieltech/haramblur/data/BlurStyle;
    ASTORE 13
   L59
    LINENUMBER 480 L59
    ALOAD 13
    ASTORE 12
   L61
    LINENUMBER 483 L61
    ALOAD 4
    LDC "expandBlurArea"
    BIPUSH 30
    INVOKEVIRTUAL org/json/JSONObject.optInt (Ljava/lang/String;I)I
    ISTORE 13
   L62
    LINENUMBER 484 L62
   L63
   L6
    NOP
   L64
    LINENUMBER 485 L64
    ALOAD 4
    LDC "processingSpeed"
    LDC "BALANCED"
    INVOKEVIRTUAL org/json/JSONObject.optString (Ljava/lang/String;Ljava/lang/String;)Ljava/lang/String;
    ASTORE 15
   L65
    ALOAD 15
    LDC "optString(...)"
    INVOKESTATIC kotlin/jvm/internal/Intrinsics.checkNotNullExpressionValue (Ljava/lang/Object;Ljava/lang/String;)V
    ALOAD 15
    INVOKESTATIC kotlin/jvm/internal/$PseudoInsn.AS_NOT_NULL (Ljava/lang/Object;)Ljava/lang/Object;
    ASTORE 15
    ALOAD 15
   L66
    CHECKCAST java/lang/String
    INVOKESTATIC com/hieltech/haramblur/data/ProcessingSpeed.valueOf (Ljava/lang/String;)Lcom/hieltech/haramblur/data/ProcessingSpeed;
    ASTORE 15
   L7
    GOTO L67
   L8
    LINENUMBER 486 L8
    ASTORE 16
   L68
    GETSTATIC com/hieltech/haramblur/data/ProcessingSpeed.BALANCED : Lcom/hieltech/haramblur/data/ProcessingSpeed;
    ASTORE 15
   L67
    LINENUMBER 484 L67
    ALOAD 15
    ASTORE 14
   L69
    LINENUMBER 487 L69
    ALOAD 4
    LDC "enableRealTimeProcessing"
    NOP
    ICONST_1
    INVOKEVIRTUAL org/json/JSONObject.optBoolean (Ljava/lang/String;Z)Z
    ISTORE 15
   L70
    LINENUMBER 488 L70
    ALOAD 4
    LDC "enableFullScreenBlurForNSFW"
    NOP
    ICONST_1
    INVOKEVIRTUAL org/json/JSONObject.optBoolean (Ljava/lang/String;Z)Z
    ISTORE 16
   L71
    LINENUMBER 489 L71
    ALOAD 4
    LDC "showBlurBorders"
    NOP
    ICONST_1
    INVOKEVIRTUAL org/json/JSONObject.optBoolean (Ljava/lang/String;Z)Z
    ISTORE 17
   L72
    LINENUMBER 490 L72
    ALOAD 4
    LDC "enableHoverToReveal"
    NOP
    ICONST_0
    INVOKEVIRTUAL org/json/JSONObject.optBoolean (Ljava/lang/String;Z)Z
    ISTORE 18
   L73
    LINENUMBER 491 L73
   L74
   L9
    NOP
   L75
    LINENUMBER 492 L75
    ALOAD 4
    LDC "genderDetectionAccuracy"
    LDC "BALANCED"
    INVOKEVIRTUAL org/json/JSONObject.optString (Ljava/lang/String;Ljava/lang/String;)Ljava/lang/String;
    ASTORE 20
   L76
    ALOAD 20
    LDC "optString(...)"
    INVOKESTATIC kotlin/jvm/internal/Intrinsics.checkNotNullExpressionValue (Ljava/lang/Object;Ljava/lang/String;)V
    ALOAD 20
    INVOKESTATIC kotlin/jvm/internal/$PseudoInsn.AS_NOT_NULL (Ljava/lang/Object;)Ljava/lang/Object;
    ASTORE 20
    ALOAD 20
   L77
    CHECKCAST java/lang/String
    INVOKESTATIC com/hieltech/haramblur/data/GenderAccuracy.valueOf (Ljava/lang/String;)Lcom/hieltech/haramblur/data/GenderAccuracy;
    ASTORE 20
   L10
    GOTO L78
   L11
    LINENUMBER 493 L11
    ASTORE 21
   L79
    GETSTATIC com/hieltech/haramblur/data/GenderAccuracy.BALANCED : Lcom/hieltech/haramblur/data/GenderAccuracy;
    ASTORE 20
   L78
    LINENUMBER 491 L78
    ALOAD 20
    ASTORE 19
   L80
    LINENUMBER 494 L80
    ALOAD 4
    LDC "contentDensityThreshold"
    LDC 0.4
    INVOKEVIRTUAL org/json/JSONObject.optDouble (Ljava/lang/String;D)D
    D2F
    FSTORE 20
   L81
    LINENUMBER 495 L81
    ALOAD 4
    LDC "mandatoryReflectionTime"
    BIPUSH 15
    INVOKEVIRTUAL org/json/JSONObject.optInt (Ljava/lang/String;I)I
    ISTORE 21
   L82
    LINENUMBER 496 L82
    ALOAD 4
    LDC "enableSiteBlocking"
    NOP
    ICONST_1
    INVOKEVIRTUAL org/json/JSONObject.optBoolean (Ljava/lang/String;Z)Z
    ISTORE 22
   L83
    LINENUMBER 497 L83
    ALOAD 4
    LDC "enableQuranicGuidance"
    NOP
    ICONST_1
    INVOKEVIRTUAL org/json/JSONObject.optBoolean (Ljava/lang/String;Z)Z
    ISTORE 23
   L84
    LINENUMBER 498 L84
    ALOAD 4
    LDC "ultraFastModeEnabled"
    NOP
    ICONST_0
    INVOKEVIRTUAL org/json/JSONObject.optBoolean (Ljava/lang/String;Z)Z
    ISTORE 24
   L85
    LINENUMBER 499 L85
    ALOAD 4
    LDC "fullScreenWarningEnabled"
    NOP
    ICONST_1
    INVOKEVIRTUAL org/json/JSONObject.optBoolean (Ljava/lang/String;Z)Z
    ISTORE 25
   L86
    LINENUMBER 500 L86
    ALOAD 4
    LDC "maxProcessingTimeMs"
    LDC 50
    INVOKEVIRTUAL org/json/JSONObject.optLong (Ljava/lang/String;J)J
    LSTORE 26
   L87
    LINENUMBER 501 L87
    ALOAD 4
    LDC "enableGPUAcceleration"
    NOP
    ICONST_1
    INVOKEVIRTUAL org/json/JSONObject.optBoolean (Ljava/lang/String;Z)Z
    ISTORE 28
   L88
    LINENUMBER 502 L88
    ALOAD 4
    LDC "frameSkipThreshold"
    ICONST_3
    INVOKEVIRTUAL org/json/JSONObject.optInt (Ljava/lang/String;I)I
    ISTORE 29
   L89
    LINENUMBER 503 L89
    ALOAD 4
    LDC "imageDownscaleRatio"
    LDC 0.5
    INVOKEVIRTUAL org/json/JSONObject.optDouble (Ljava/lang/String;D)D
    D2F
    FSTORE 30
   L90
    LINENUMBER 504 L90
   L91
   L12
    NOP
   L92
    LINENUMBER 506 L92
    ALOAD 4
    LDC "preferredLanguage"
    LDC "ENGLISH"
    INVOKEVIRTUAL org/json/JSONObject.optString (Ljava/lang/String;Ljava/lang/String;)Ljava/lang/String;
    ASTORE 32
   L93
    ALOAD 32
    LDC "optString(...)"
    INVOKESTATIC kotlin/jvm/internal/Intrinsics.checkNotNullExpressionValue (Ljava/lang/Object;Ljava/lang/String;)V
    ALOAD 32
    INVOKESTATIC kotlin/jvm/internal/$PseudoInsn.AS_NOT_NULL (Ljava/lang/Object;)Ljava/lang/Object;
    ASTORE 32
    ALOAD 32
   L94
    CHECKCAST java/lang/String
   L95
    LINENUMBER 505 L95
    INVOKESTATIC com/hieltech/haramblur/detection/Language.valueOf (Ljava/lang/String;)Lcom/hieltech/haramblur/detection/Language;
    ASTORE 32
   L13
    GOTO L96
   L14
    LINENUMBER 508 L14
    ASTORE 33
   L97
    GETSTATIC com/hieltech/haramblur/detection/Language.ENGLISH : Lcom/hieltech/haramblur/detection/Language;
    ASTORE 32
   L96
    LINENUMBER 504 L96
    ALOAD 32
    ASTORE 31
   L98
    LINENUMBER 509 L98
    ALOAD 4
    LDC "verseDisplayDuration"
    BIPUSH 10
    INVOKEVIRTUAL org/json/JSONObject.optInt (Ljava/lang/String;I)I
    ISTORE 32
   L99
    LINENUMBER 510 L99
    ALOAD 4
    LDC "enableArabicText"
    NOP
    ICONST_1
    INVOKEVIRTUAL org/json/JSONObject.optBoolean (Ljava/lang/String;Z)Z
    ISTORE 33
   L100
    LINENUMBER 511 L100
    ALOAD 4
    LDC "customReflectionTime"
    BIPUSH 15
    INVOKEVIRTUAL org/json/JSONObject.optInt (Ljava/lang/String;I)I
    ISTORE 34
   L101
    LINENUMBER 512 L101
    ALOAD 4
    LDC "genderConfidenceThreshold"
    LDC 0.4
    INVOKEVIRTUAL org/json/JSONObject.optDouble (Ljava/lang/String;D)D
    D2F
    FSTORE 35
   L102
    LINENUMBER 513 L102
    ALOAD 4
    LDC "nsfwConfidenceThreshold"
    LDC 0.5
    INVOKEVIRTUAL org/json/JSONObject.optDouble (Ljava/lang/String;D)D
    D2F
    FSTORE 36
   L103
    LINENUMBER 514 L103
    ALOAD 4
    LDC "enableFallbackDetection"
    NOP
    ICONST_1
    INVOKEVIRTUAL org/json/JSONObject.optBoolean (Ljava/lang/String;Z)Z
    ISTORE 37
   L104
    LINENUMBER 515 L104
    ALOAD 4
    LDC "enablePerformanceMonitoring"
    NOP
    ICONST_1
    INVOKEVIRTUAL org/json/JSONObject.optBoolean (Ljava/lang/String;Z)Z
    ISTORE 38
   L105
    LINENUMBER 517 L105
    ALOAD 4
    LDC "enableDetailedLogging"
    NOP
    ICONST_1
    INVOKEVIRTUAL org/json/JSONObject.optBoolean (Ljava/lang/String;Z)Z
    ISTORE 39
   L106
    LINENUMBER 518 L106
   L107
   L15
    NOP
   L108
    LINENUMBER 519 L108
    ALOAD 4
    LDC "logLevel"
    LDC "INFO"
    INVOKEVIRTUAL org/json/JSONObject.optString (Ljava/lang/String;Ljava/lang/String;)Ljava/lang/String;
    ASTORE 41
   L109
    ALOAD 41
    LDC "optString(...)"
    INVOKESTATIC kotlin/jvm/internal/Intrinsics.checkNotNullExpressionValue (Ljava/lang/Object;Ljava/lang/String;)V
    ALOAD 41
    INVOKESTATIC kotlin/jvm/internal/$PseudoInsn.AS_NOT_NULL (Ljava/lang/Object;)Ljava/lang/Object;
    ASTORE 41
    ALOAD 41
   L110
    CHECKCAST java/lang/String
    INVOKESTATIC com/hieltech/haramblur/data/LogLevel.valueOf (Ljava/lang/String;)Lcom/hieltech/haramblur/data/LogLevel;
    ASTORE 41
   L16
    GOTO L111
   L17
    LINENUMBER 520 L17
    ASTORE 42
   L112
    GETSTATIC com/hieltech/haramblur/data/LogLevel.INFO : Lcom/hieltech/haramblur/data/LogLevel;
    ASTORE 41
   L111
    LINENUMBER 518 L111
    ALOAD 41
    ASTORE 40
   L113
    LINENUMBER 521 L113
    ALOAD 4
    LDC "enablePerformanceLogging"
    NOP
    ICONST_1
    INVOKEVIRTUAL org/json/JSONObject.optBoolean (Ljava/lang/String;Z)Z
    ISTORE 41
   L114
    LINENUMBER 522 L114
    ALOAD 4
    LDC "enableErrorReporting"
    NOP
    ICONST_1
    INVOKEVIRTUAL org/json/JSONObject.optBoolean (Ljava/lang/String;Z)Z
    ISTORE 42
   L115
    LINENUMBER 523 L115
    ALOAD 4
    LDC "enableUserActionLogging"
    NOP
    ICONST_1
    INVOKEVIRTUAL org/json/JSONObject.optBoolean (Ljava/lang/String;Z)Z
    ISTORE 43
   L116
    LINENUMBER 524 L116
    ALOAD 4
    LDC "maxLogRetentionDays"
    BIPUSH 7
    INVOKEVIRTUAL org/json/JSONObject.optInt (Ljava/lang/String;I)I
    ISTORE 44
   L117
    LINENUMBER 525 L117
    ALOAD 4
    LDC "enableEnhancedBlocking"
    NOP
    ICONST_0
    INVOKEVIRTUAL org/json/JSONObject.optBoolean (Ljava/lang/String;Z)Z
    ISTORE 45
   L118
    LINENUMBER 526 L118
   L119
   L18
    NOP
   L120
    LINENUMBER 528 L120
    ALOAD 4
    LDC "preferredBlockingMethod"
    LDC "ADAPTIVE"
    INVOKEVIRTUAL org/json/JSONObject.optString (Ljava/lang/String;Ljava/lang/String;)Ljava/lang/String;
    ASTORE 47
   L121
    ALOAD 47
    LDC "optString(...)"
    INVOKESTATIC kotlin/jvm/internal/Intrinsics.checkNotNullExpressionValue (Ljava/lang/Object;Ljava/lang/String;)V
    ALOAD 47
    INVOKESTATIC kotlin/jvm/internal/$PseudoInsn.AS_NOT_NULL (Ljava/lang/Object;)Ljava/lang/Object;
    ASTORE 47
    ALOAD 47
   L122
    CHECKCAST java/lang/String
   L123
    LINENUMBER 527 L123
    INVOKESTATIC com/hieltech/haramblur/detection/BlockingMethod.valueOf (Ljava/lang/String;)Lcom/hieltech/haramblur/detection/BlockingMethod;
    ASTORE 47
   L19
    GOTO L124
   L20
    LINENUMBER 530 L20
    ASTORE 48
   L125
    GETSTATIC com/hieltech/haramblur/detection/BlockingMethod.ADAPTIVE : Lcom/hieltech/haramblur/detection/BlockingMethod;
    ASTORE 47
   L124
    LINENUMBER 526 L124
    ALOAD 47
    ASTORE 46
   L126
    LINENUMBER 531 L126
    ALOAD 4
    LDC "forceCloseTimeout"
    LDC 5000
    INVOKEVIRTUAL org/json/JSONObject.optLong (Ljava/lang/String;J)J
    LSTORE 47
   L127
    LINENUMBER 532 L127
    ALOAD 4
    LDC "settingsVersion"
    ICONST_3
    INVOKEVIRTUAL org/json/JSONObject.optInt (Ljava/lang/String;I)I
    ISTORE 49
   L128
    LINENUMBER 471 L128
    NEW com/hieltech/haramblur/data/AppSettings
    DUP
   L129
    LINENUMBER 472 L129
    ILOAD 6
   L130
    LINENUMBER 473 L130
    ILOAD 7
   L131
    LINENUMBER 474 L131
    ILOAD 8
   L132
    LINENUMBER 475 L132
    ILOAD 9
   L133
    LINENUMBER 476 L133
    FLOAD 10
   L134
    LINENUMBER 477 L134
    ALOAD 11
   L135
    LINENUMBER 480 L135
    ALOAD 12
   L136
    LINENUMBER 483 L136
    ILOAD 13
   L137
    LINENUMBER 484 L137
    ALOAD 14
   L138
    LINENUMBER 487 L138
    ILOAD 15
   L139
    LINENUMBER 471 L139
    ACONST_NULL
   L140
    LINENUMBER 488 L140
    ILOAD 16
   L141
    LINENUMBER 489 L141
    ILOAD 17
   L142
    LINENUMBER 490 L142
    ILOAD 18
   L143
    LINENUMBER 491 L143
    ALOAD 19
   L144
    LINENUMBER 471 L144
    NOP
    ICONST_0
   L145
    LINENUMBER 494 L145
    FLOAD 20
   L146
    LINENUMBER 495 L146
    ILOAD 21
   L147
    LINENUMBER 496 L147
    ILOAD 22
   L148
    LINENUMBER 497 L148
    ILOAD 23
   L149
    LINENUMBER 498 L149
    ILOAD 24
   L150
    LINENUMBER 499 L150
    ILOAD 25
   L151
    LINENUMBER 500 L151
    LLOAD 26
   L152
    LINENUMBER 501 L152
    ILOAD 28
   L153
    LINENUMBER 502 L153
    ILOAD 29
   L154
    LINENUMBER 503 L154
    FLOAD 30
   L155
    LINENUMBER 504 L155
    ALOAD 31
   L156
    LINENUMBER 509 L156
    ILOAD 32
   L157
    LINENUMBER 510 L157
    ILOAD 33
   L158
    LINENUMBER 511 L158
    ILOAD 34
   L159
    LINENUMBER 512 L159
    FLOAD 35
   L160
    LINENUMBER 513 L160
    FLOAD 36
   L161
    LINENUMBER 514 L161
    ILOAD 37
   L162
    LINENUMBER 515 L162
    ILOAD 38
   L163
    LINENUMBER 471 L163
    NOP
    ICONST_0
    ICONST_0
    FCONST_0
    ICONST_0
    FCONST_0
    LCONST_0
   L164
    LINENUMBER 517 L164
    ILOAD 39
   L165
    LINENUMBER 518 L165
    ALOAD 40
   L166
    LINENUMBER 471 L166
    ACONST_NULL
   L167
    LINENUMBER 524 L167
    ILOAD 44
   L168
    LINENUMBER 521 L168
    ILOAD 41
   L169
    LINENUMBER 522 L169
    ILOAD 42
   L170
    LINENUMBER 523 L170
    ILOAD 43
   L171
    LINENUMBER 525 L171
    ILOAD 45
   L172
    LINENUMBER 471 L172
    NOP
    ICONST_0
    NOP
    ICONST_0
   L173
    LINENUMBER 526 L173
    ALOAD 46
   L174
    LINENUMBER 531 L174
    LLOAD 47
   L175
    LINENUMBER 471 L175
    NOP
    ICONST_0
    NOP
    ICONST_0
    LCONST_0
    NOP
    ICONST_0
    ACONST_NULL
    LCONST_0
    NOP
    ICONST_0
    NOP
    ICONST_0
    NOP
    ICONST_0
    NOP
    ICONST_0
    NOP
    ICONST_0
    ICONST_0
    ICONST_0
    ICONST_0
    ICONST_0
    ICONST_0
    ICONST_0
    NOP
    ICONST_0
    NOP
    ICONST_0
    ACONST_NULL
    NOP
    ICONST_0
    NOP
    ICONST_0
   L176
    LINENUMBER 532 L176
    ILOAD 49
   L177
    LINENUMBER 471 L177
    LDC 33792
    LDC -850692
    SIPUSH 1023
    ACONST_NULL
    INVOKESPECIAL com/hieltech/haramblur/data/AppSettings.<init> (ZZZZFLcom/hieltech/haramblur/data/BlurIntensity;Lcom/hieltech/haramblur/data/BlurStyle;ILcom/hieltech/haramblur/data/ProcessingSpeed;ZLjava/util/Set;ZZZLcom/hieltech/haramblur/data/GenderAccuracy;ZFIZZZZJZIFLcom/hieltech/haramblur/detection/Language;IZIFFZZZIFIFJZLcom/hieltech/haramblur/data/LogLevel;Ljava/util/Set;IZZZZZZLcom/hieltech/haramblur/detection/BlockingMethod;JZZJZLjava/lang/String;JZZZZZIIIIIIZZLjava/lang/String;ZZIIIILkotlin/jvm/internal/DefaultConstructorMarker;)V
   L178
    ASTORE 5
   L179
    LINENUMBER 535 L179
   L180
    LINENUMBER 536 L180
    ALOAD 3
    LDC "name"
    INVOKEVIRTUAL org/json/JSONObject.getString (Ljava/lang/String;)Ljava/lang/String;
    ASTORE 7
   L181
    ALOAD 7
    LDC "getString(...)"
    INVOKESTATIC kotlin/jvm/internal/Intrinsics.checkNotNullExpressionValue (Ljava/lang/Object;Ljava/lang/String;)V
    ALOAD 7
    INVOKESTATIC kotlin/jvm/internal/$PseudoInsn.AS_NOT_NULL (Ljava/lang/Object;)Ljava/lang/Object;
    ASTORE 7
    ALOAD 7
   L182
    CHECKCAST java/lang/String
   L183
    LINENUMBER 537 L183
    ALOAD 3
    LDC "description"
    LDC ""
    INVOKEVIRTUAL org/json/JSONObject.optString (Ljava/lang/String;Ljava/lang/String;)Ljava/lang/String;
    ASTORE 7
   L184
    ALOAD 7
    LDC "optString(...)"
    INVOKESTATIC kotlin/jvm/internal/Intrinsics.checkNotNullExpressionValue (Ljava/lang/Object;Ljava/lang/String;)V
    ALOAD 7
    INVOKESTATIC kotlin/jvm/internal/$PseudoInsn.AS_NOT_NULL (Ljava/lang/Object;)Ljava/lang/Object;
    ASTORE 7
    ALOAD 7
   L185
    CHECKCAST java/lang/String
   L186
    LINENUMBER 538 L186
    ALOAD 3
    LDC "version"
    ICONST_3
    INVOKEVIRTUAL org/json/JSONObject.optInt (Ljava/lang/String;I)I
   L187
    LINENUMBER 539 L187
    ALOAD 5
   L188
    LINENUMBER 541 L188
   L189
    ASTORE 55
    ISTORE 54
    ASTORE 53
    ASTORE 52
   L21
    NOP
    ALOAD 52
    ALOAD 53
    ILOAD 54
    ALOAD 55
   L190
    LINENUMBER 542 L190
    ALOAD 3
    LDC "metadata"
    INVOKEVIRTUAL org/json/JSONObject.getJSONObject (Ljava/lang/String;)Lorg/json/JSONObject;
    LDC "category"
    LDC "CUSTOM"
    INVOKEVIRTUAL org/json/JSONObject.optString (Ljava/lang/String;Ljava/lang/String;)Ljava/lang/String;
    ASTORE 8
   L191
    ALOAD 8
    LDC "optString(...)"
    INVOKESTATIC kotlin/jvm/internal/Intrinsics.checkNotNullExpressionValue (Ljava/lang/Object;Ljava/lang/String;)V
    ALOAD 8
    INVOKESTATIC kotlin/jvm/internal/$PseudoInsn.AS_NOT_NULL (Ljava/lang/Object;)Ljava/lang/Object;
    ASTORE 8
    ALOAD 8
   L192
    CHECKCAST java/lang/String
    INVOKESTATIC com/hieltech/haramblur/data/PresetCategory.valueOf (Ljava/lang/String;)Lcom/hieltech/haramblur/data/PresetCategory;
    ASTORE 8
   L22
    GOTO L193
   L23
    LINENUMBER 543 L23
    ASTORE 9
    ALOAD 52
    ALOAD 53
    ILOAD 54
    ALOAD 55
   L194
    GETSTATIC com/hieltech/haramblur/data/PresetCategory.CUSTOM : Lcom/hieltech/haramblur/data/PresetCategory;
    ASTORE 8
   L193
    LINENUMBER 541 L193
    ALOAD 8
    ASTORE 7
   L195
    LINENUMBER 544 L195
   L196
    ASTORE 55
    ISTORE 54
    ASTORE 53
    ASTORE 52
   L24
    NOP
    ALOAD 52
    ALOAD 53
    ILOAD 54
    ALOAD 55
   L197
    LINENUMBER 545 L197
    ALOAD 3
    LDC "metadata"
    INVOKEVIRTUAL org/json/JSONObject.getJSONObject (Ljava/lang/String;)Lorg/json/JSONObject;
    LDC "difficulty"
    LDC "INTERMEDIATE"
    INVOKEVIRTUAL org/json/JSONObject.optString (Ljava/lang/String;Ljava/lang/String;)Ljava/lang/String;
    ASTORE 9
   L198
    ALOAD 9
    LDC "optString(...)"
    INVOKESTATIC kotlin/jvm/internal/Intrinsics.checkNotNullExpressionValue (Ljava/lang/Object;Ljava/lang/String;)V
    ALOAD 9
    INVOKESTATIC kotlin/jvm/internal/$PseudoInsn.AS_NOT_NULL (Ljava/lang/Object;)Ljava/lang/Object;
    ASTORE 9
    ALOAD 9
   L199
    CHECKCAST java/lang/String
    INVOKESTATIC com/hieltech/haramblur/data/PresetDifficulty.valueOf (Ljava/lang/String;)Lcom/hieltech/haramblur/data/PresetDifficulty;
    ASTORE 9
   L25
    GOTO L200
   L26
    LINENUMBER 546 L26
    ASTORE 10
    ALOAD 52
    ALOAD 53
    ILOAD 54
    ALOAD 55
   L201
    GETSTATIC com/hieltech/haramblur/data/PresetDifficulty.INTERMEDIATE : Lcom/hieltech/haramblur/data/PresetDifficulty;
    ASTORE 9
   L200
    LINENUMBER 544 L200
    ALOAD 9
    ASTORE 8
   L202
    LINENUMBER 547 L202
    ALOAD 3
    LDC "metadata"
    INVOKEVIRTUAL org/json/JSONObject.getJSONObject (Ljava/lang/String;)Lorg/json/JSONObject;
    LDC "useCase"
    LDC "Custom configuration"
    INVOKEVIRTUAL org/json/JSONObject.optString (Ljava/lang/String;Ljava/lang/String;)Ljava/lang/String;
    ASTORE 10
   L203
    ALOAD 10
    LDC "optString(...)"
    INVOKESTATIC kotlin/jvm/internal/Intrinsics.checkNotNullExpressionValue (Ljava/lang/Object;Ljava/lang/String;)V
    ALOAD 10
    INVOKESTATIC kotlin/jvm/internal/$PseudoInsn.AS_NOT_NULL (Ljava/lang/Object;)Ljava/lang/Object;
    ASTORE 10
    ALOAD 10
   L204
    CHECKCAST java/lang/String
    ASTORE 9
   L205
    LINENUMBER 548 L205
    ALOAD 3
    LDC "metadata"
    INVOKEVIRTUAL org/json/JSONObject.getJSONObject (Ljava/lang/String;)Lorg/json/JSONObject;
    LDC "author"
    LDC "Unknown"
    INVOKEVIRTUAL org/json/JSONObject.optString (Ljava/lang/String;Ljava/lang/String;)Ljava/lang/String;
    ASTORE 11
   L206
    ALOAD 11
    LDC "optString(...)"
    INVOKESTATIC kotlin/jvm/internal/Intrinsics.checkNotNullExpressionValue (Ljava/lang/Object;Ljava/lang/String;)V
    ALOAD 11
    INVOKESTATIC kotlin/jvm/internal/$PseudoInsn.AS_NOT_NULL (Ljava/lang/Object;)Ljava/lang/Object;
    ASTORE 11
    ALOAD 11
   L207
    CHECKCAST java/lang/String
    ASTORE 10
   L208
    LINENUMBER 549 L208
    ALOAD 3
    LDC "metadata"
    INVOKEVIRTUAL org/json/JSONObject.getJSONObject (Ljava/lang/String;)Lorg/json/JSONObject;
    LDC "isBuiltIn"
    NOP
    ICONST_0
    INVOKEVIRTUAL org/json/JSONObject.optBoolean (Ljava/lang/String;Z)Z
    ISTORE 11
   L209
    LINENUMBER 550 L209
    ALOAD 3
    LDC "metadata"
    INVOKEVIRTUAL org/json/JSONObject.getJSONObject (Ljava/lang/String;)Lorg/json/JSONObject;
    LDC "tags"
    LDC ""
    INVOKEVIRTUAL org/json/JSONObject.optString (Ljava/lang/String;Ljava/lang/String;)Ljava/lang/String;
    ASTORE 13
   L210
    ALOAD 13
    LDC "optString(...)"
    INVOKESTATIC kotlin/jvm/internal/Intrinsics.checkNotNullExpressionValue (Ljava/lang/Object;Ljava/lang/String;)V
    ALOAD 13
    INVOKESTATIC kotlin/jvm/internal/$PseudoInsn.AS_NOT_NULL (Ljava/lang/Object;)Ljava/lang/Object;
    ASTORE 13
    ALOAD 13
   L211
    CHECKCAST java/lang/CharSequence
    ICONST_1
    ANEWARRAY java/lang/String
    ASTORE 13
   L212
    ALOAD 13
    ICONST_0
    LDC ","
    AASTORE
    ALOAD 13
   L213
    NOP
    ICONST_0
    ICONST_0
    BIPUSH 6
    ACONST_NULL
    INVOKESTATIC kotlin/text/StringsKt.split$default (Ljava/lang/CharSequence;[Ljava/lang/String;ZIILjava/lang/Object;)Ljava/util/List;
    CHECKCAST java/lang/Iterable
    ASTORE 13
    ASTORE 55
    ISTORE 54
    ASTORE 53
    ASTORE 52
    NOP
   L214
    ICONST_0
    ISTORE 14
   L215
    LINENUMBER 752 L215
    ALOAD 13
    ASTORE 15
    NEW java/util/ArrayList
    DUP
    INVOKESPECIAL java/util/ArrayList.<init> ()V
    CHECKCAST java/util/Collection
    ASTORE 16
   L216
    ICONST_0
    ISTORE 17
   L217
    LINENUMBER 753 L217
    ALOAD 15
    INVOKEINTERFACE java/lang/Iterable.iterator ()Ljava/util/Iterator; (itf)
    ASTORE 18
   L218
    ALOAD 18
    INVOKEINTERFACE java/util/Iterator.hasNext ()Z (itf)
    IFEQ L219
    ALOAD 18
    INVOKEINTERFACE java/util/Iterator.next ()Ljava/lang/Object; (itf)
    ASTORE 19
   L220
    ALOAD 19
    CHECKCAST java/lang/String
    ASTORE 20
   L221
    ICONST_0
    ISTORE 21
   L222
    NOP
   L223
    LINENUMBER 550 L223
    ALOAD 20
    CHECKCAST java/lang/CharSequence
    INVOKESTATIC kotlin/text/StringsKt.isBlank (Ljava/lang/CharSequence;)Z
    IFNE L224
    ICONST_1
    GOTO L225
   L224
    ICONST_0
   L225
    GOTO L226
   L226
    LINENUMBER 550 L226
    NOP
    GOTO L227
   L227
    INVOKESTATIC java/lang/Boolean.valueOf (Z)Ljava/lang/Boolean;
   L228
    LINENUMBER 753 L228
    CHECKCAST java/lang/Boolean
    INVOKEVIRTUAL java/lang/Boolean.booleanValue ()Z
    IFEQ L218
    ALOAD 16
    ALOAD 19
    INVOKEINTERFACE java/util/Collection.add (Ljava/lang/Object;)Z (itf)
    POP
   L229
    GOTO L218
   L219
    LINENUMBER 754 L219
    ALOAD 16
   L230
    CHECKCAST java/util/List
   L231
    LINENUMBER 752 L231
    NOP
    GOTO L232
   L232
    ASTORE 56
    ALOAD 52
    ALOAD 53
    ILOAD 54
    ALOAD 55
    ALOAD 56
    CHECKCAST java/lang/Iterable
   L233
    LINENUMBER 550 L233
    INVOKESTATIC kotlin/collections/CollectionsKt.toSet (Ljava/lang/Iterable;)Ljava/util/Set;
    ASTORE 12
   L234
    LINENUMBER 540 L234
    NEW com/hieltech/haramblur/data/PresetMetadata
    DUP
   L235
    LINENUMBER 541 L235
    ALOAD 7
   L236
    LINENUMBER 544 L236
    ALOAD 8
   L237
    LINENUMBER 547 L237
    ALOAD 9
   L238
    LINENUMBER 548 L238
    ALOAD 10
   L239
    LINENUMBER 550 L239
    ALOAD 12
   L240
    LINENUMBER 549 L240
    ILOAD 11
   L241
    LINENUMBER 540 L241
    INVOKESPECIAL com/hieltech/haramblur/data/PresetMetadata.<init> (Lcom/hieltech/haramblur/data/PresetCategory;Lcom/hieltech/haramblur/data/PresetDifficulty;Ljava/lang/String;Ljava/lang/String;Ljava/util/Set;Z)V
   L242
    LINENUMBER 552 L242
    ALOAD 3
    LDC "creationTimestamp"
    INVOKESTATIC java/lang/System.currentTimeMillis ()J
    INVOKEVIRTUAL org/json/JSONObject.optLong (Ljava/lang/String;J)J
   L243
    LINENUMBER 535 L243
    LSTORE 57
    ASTORE 59
    ASTORE 60
    ISTORE 61
    ASTORE 62
    ASTORE 63
    NEW com/hieltech/haramblur/data/PresetData
    DUP
    ALOAD 63
    ALOAD 62
    ILOAD 61
    ALOAD 60
    ALOAD 59
    LLOAD 57
    INVOKESPECIAL com/hieltech/haramblur/data/PresetData.<init> (Ljava/lang/String;Ljava/lang/String;ILcom/hieltech/haramblur/data/AppSettings;Lcom/hieltech/haramblur/data/PresetMetadata;J)V
    ASTORE 6
   L244
    LINENUMBER 555 L244
    NEW com/hieltech/haramblur/data/PresetImportResult$Success
    DUP
    ALOAD 6
    INVOKESPECIAL com/hieltech/haramblur/data/PresetImportResult$Success.<init> (Lcom/hieltech/haramblur/data/PresetData;)V
   L245
    CHECKCAST com/hieltech/haramblur/data/PresetImportResult
    ASTORE 3
   L28
    GOTO L246
   L29
    LINENUMBER 556 L29
    ASTORE 4
   L247
    LINENUMBER 557 L247
    LDC "SettingsViewModel"
    LDC "Failed to import preset"
    ALOAD 4
    CHECKCAST java/lang/Throwable
    INVOKESTATIC android/util/Log.e (Ljava/lang/String;Ljava/lang/String;Ljava/lang/Throwable;)I
    POP
   L248
    LINENUMBER 558 L248
    NEW com/hieltech/haramblur/data/PresetImportResult$Error
    DUP
    ALOAD 4
    INVOKEVIRTUAL java/lang/Exception.getMessage ()Ljava/lang/String;
    INVOKEDYNAMIC makeConcatWithConstants(Ljava/lang/String;)Ljava/lang/String; [
      // handle kind 0x6 : INVOKESTATIC
      java/lang/invoke/StringConcatFactory.makeConcatWithConstants(Ljava/lang/invoke/MethodHandles$Lookup;Ljava/lang/String;Ljava/lang/invoke/MethodType;Ljava/lang/String;[Ljava/lang/Object;)Ljava/lang/invoke/CallSite;
      // arguments:
      "Failed to parse preset: \u0001"
    ]
    GETSTATIC com/hieltech/haramblur/data/ImportErrorType.INVALID_JSON : Lcom/hieltech/haramblur/data/ImportErrorType;
    INVOKESPECIAL com/hieltech/haramblur/data/PresetImportResult$Error.<init> (Ljava/lang/String;Lcom/hieltech/haramblur/data/ImportErrorType;)V
    CHECKCAST com/hieltech/haramblur/data/PresetImportResult
    ASTORE 3
   L246
    ALOAD 3
   L249
    LINENUMBER 467 L249
    ARETURN
   L250
    NOP
   L251
    LOCALVARIABLE e Ljava/lang/IllegalArgumentException; L53 L52 13
    LOCALVARIABLE e Ljava/lang/IllegalArgumentException; L60 L59 14
    LOCALVARIABLE e Ljava/lang/IllegalArgumentException; L68 L67 16
    LOCALVARIABLE e Ljava/lang/IllegalArgumentException; L79 L78 21
    LOCALVARIABLE e Ljava/lang/IllegalArgumentException; L97 L96 33
    LOCALVARIABLE e Ljava/lang/IllegalArgumentException; L112 L111 42
    LOCALVARIABLE e Ljava/lang/IllegalArgumentException; L125 L124 48
    LOCALVARIABLE e Ljava/lang/Exception; L194 L193 9
    LOCALVARIABLE e Ljava/lang/Exception; L201 L200 10
    LOCALVARIABLE $i$a$-filter-SettingsViewModel$importPreset$preset$1\3\753\0 I L222 L227 21
    LOCALVARIABLE it\3 Ljava/lang/String; L221 L227 20
    LOCALVARIABLE element\2 Ljava/lang/Object; L220 L229 19
    LOCALVARIABLE $i$f$filterTo\2\752 I L217 L230 17
    LOCALVARIABLE $this$filterTo\2 Ljava/lang/Iterable; L216 L230 15
    LOCALVARIABLE destination\2 Ljava/util/Collection; L216 L230 16
    LOCALVARIABLE $i$f$filter\1\550 I L215 L232 14
    LOCALVARIABLE $this$filter\1 Ljava/lang/Iterable; L214 L232 13
    LOCALVARIABLE jsonObject Lorg/json/JSONObject; L41 L245 3
    LOCALVARIABLE settingsJson Lorg/json/JSONObject; L42 L245 4
    LOCALVARIABLE importedSettings Lcom/hieltech/haramblur/data/AppSettings; L179 L245 5
    LOCALVARIABLE preset Lcom/hieltech/haramblur/data/PresetData; L244 L245 6
    LOCALVARIABLE e Ljava/lang/Exception; L247 L246 4
    LOCALVARIABLE validation Lcom/hieltech/haramblur/data/ValidationResult; L32 L251 2
    LOCALVARIABLE this Lcom/hieltech/haramblur/ui/SettingsViewModel; L30 L251 0
    LOCALVARIABLE presetJson Ljava/lang/String; L30 L251 1
    MAXSTACK = 86
    MAXLOCALS = 64

File is unknown
The root cause java.lang.OutOfMemoryError was thrown at: org.jetbrains.org.objectweb.asm.tree.analysis.Frame.<init>(Frame.java:78)
	at org.jetbrains.kotlin.codegen.TransformationMethodVisitor.visitEnd(TransformationMethodVisitor.kt:89)
	at org.jetbrains.org.objectweb.asm.MethodVisitor.visitEnd(MethodVisitor.java:783)
	at org.jetbrains.org.objectweb.asm.tree.MethodNode.accept(MethodNode.java:772)
	at org.jetbrains.kotlin.backend.jvm.codegen.ClassCodegen.generateMethod(ClassCodegen.kt:453)
	at org.jetbrains.kotlin.backend.jvm.codegen.ClassCodegen.generate(ClassCodegen.kt:168)
	at org.jetbrains.kotlin.backend.jvm.FileCodegen.lower(JvmPhases.kt:39)
	at org.jetbrains.kotlin.backend.common.phaser.PhaseFactoriesKt.createFilePhase$lambda$4(PhaseFactories.kt:71)
	at org.jetbrains.kotlin.backend.common.phaser.PhaseBuildersKt$createSimpleNamedCompilerPhase$1.phaseBody(PhaseBuilders.kt:69)
	at org.jetbrains.kotlin.backend.common.phaser.SimpleNamedCompilerPhase.phaseBody(CompilerPhase.kt:226)
	at org.jetbrains.kotlin.backend.common.phaser.AbstractNamedCompilerPhase.invoke(CompilerPhase.kt:113)
	at org.jetbrains.kotlin.backend.common.phaser.PerformByIrFilePhase.invokeSequential(performByIrFile.kt:62)
	at org.jetbrains.kotlin.backend.common.phaser.PerformByIrFilePhase.invoke(performByIrFile.kt:52)
	at org.jetbrains.kotlin.backend.common.phaser.PerformByIrFilePhase.invoke(performByIrFile.kt:38)
	at org.jetbrains.kotlin.backend.common.phaser.NamedCompilerPhase.phaseBody(CompilerPhase.kt:166)
	at org.jetbrains.kotlin.backend.common.phaser.AbstractNamedCompilerPhase.invoke(CompilerPhase.kt:113)
	at org.jetbrains.kotlin.backend.common.phaser.CompositePhase.invoke(PhaseBuilders.kt:27)
	at org.jetbrains.kotlin.backend.common.phaser.CompositePhase.invoke(PhaseBuilders.kt:14)
	at org.jetbrains.kotlin.backend.common.phaser.NamedCompilerPhase.phaseBody(CompilerPhase.kt:166)
	at org.jetbrains.kotlin.backend.common.phaser.AbstractNamedCompilerPhase.invoke(CompilerPhase.kt:113)
	at org.jetbrains.kotlin.backend.common.phaser.CompilerPhaseKt.invokeToplevel(CompilerPhase.kt:62)
	at org.jetbrains.kotlin.backend.jvm.JvmIrCodegenFactory.invokeCodegen(JvmIrCodegenFactory.kt:371)
	at org.jetbrains.kotlin.codegen.CodegenFactory.generateModule(CodegenFactory.kt:47)
	at org.jetbrains.kotlin.backend.jvm.JvmIrCodegenFactory.generateModuleInFrontendIRMode(JvmIrCodegenFactory.kt:433)
	at org.jetbrains.kotlin.cli.jvm.compiler.pipeline.JvmCompilerPipelineKt.generateCodeFromIr(jvmCompilerPipeline.kt:246)
	at org.jetbrains.kotlin.cli.jvm.compiler.pipeline.JvmCompilerPipelineKt.compileModulesUsingFrontendIrAndLightTree(jvmCompilerPipeline.kt:142)
	at org.jetbrains.kotlin.cli.jvm.K2JVMCompiler.doExecute(K2JVMCompiler.kt:148)
	at org.jetbrains.kotlin.cli.jvm.K2JVMCompiler.doExecute(K2JVMCompiler.kt:43)
	at org.jetbrains.kotlin.cli.common.CLICompiler.execImpl(CLICompiler.kt:103)
	at org.jetbrains.kotlin.cli.common.CLICompiler.execImpl(CLICompiler.kt:49)
	at org.jetbrains.kotlin.cli.common.CLITool.exec(CLITool.kt:101)
	at org.jetbrains.kotlin.incremental.IncrementalJvmCompilerRunner.runCompiler(IncrementalJvmCompilerRunner.kt:464)
	at org.jetbrains.kotlin.incremental.IncrementalJvmCompilerRunner.runCompiler(IncrementalJvmCompilerRunner.kt:73)
	at org.jetbrains.kotlin.incremental.IncrementalCompilerRunner.doCompile(IncrementalCompilerRunner.kt:506)
	at org.jetbrains.kotlin.incremental.IncrementalCompilerRunner.compileImpl(IncrementalCompilerRunner.kt:423)
	at org.jetbrains.kotlin.incremental.IncrementalCompilerRunner.compileNonIncrementally(IncrementalCompilerRunner.kt:301)
	at org.jetbrains.kotlin.incremental.IncrementalCompilerRunner.compile(IncrementalCompilerRunner.kt:129)
	at org.jetbrains.kotlin.daemon.CompileServiceImplBase.execIncrementalCompiler(CompileServiceImpl.kt:675)
	at org.jetbrains.kotlin.daemon.CompileServiceImplBase.access$execIncrementalCompiler(CompileServiceImpl.kt:92)
	at org.jetbrains.kotlin.daemon.CompileServiceImpl.compile(CompileServiceImpl.kt:1660)
	at jdk.internal.reflect.GeneratedMethodAccessor91.invoke(Unknown Source)
	at java.base/jdk.internal.reflect.DelegatingMethodAccessorImpl.invoke(DelegatingMethodAccessorImpl.java:43)
	at java.base/java.lang.reflect.Method.invoke(Method.java:569)
	at java.rmi/sun.rmi.server.UnicastServerRef.dispatch(UnicastServerRef.java:360)
	at java.rmi/sun.rmi.transport.Transport$1.run(Transport.java:200)
	at java.rmi/sun.rmi.transport.Transport$1.run(Transport.java:197)
	at java.base/java.security.AccessController.doPrivileged(AccessController.java:712)
	at java.rmi/sun.rmi.transport.Transport.serviceCall(Transport.java:196)
	at java.rmi/sun.rmi.transport.tcp.TCPTransport.handleMessages(TCPTransport.java:587)
	at java.rmi/sun.rmi.transport.tcp.TCPTransport$ConnectionHandler.run0(TCPTransport.java:828)
	at java.rmi/sun.rmi.transport.tcp.TCPTransport$ConnectionHandler.lambda$run$0(TCPTransport.java:705)
	at java.base/java.security.AccessController.doPrivileged(AccessController.java:399)
	at java.rmi/sun.rmi.transport.tcp.TCPTransport$ConnectionHandler.run(TCPTransport.java:704)
	at java.base/java.util.concurrent.ThreadPoolExecutor.runWorker(ThreadPoolExecutor.java:1136)
	at java.base/java.util.concurrent.ThreadPoolExecutor$Worker.run(ThreadPoolExecutor.java:635)
	at java.base/java.lang.Thread.run(Thread.java:840)
Caused by: java.lang.OutOfMemoryError: GC overhead limit exceeded
	at org.jetbrains.org.objectweb.asm.tree.analysis.Frame.<init>(Frame.java:78)
	at org.jetbrains.kotlin.codegen.optimization.common.FastMethodAnalyzer._init_$lambda$0(FastMethodAnalyzer.kt:47)
	at org.jetbrains.kotlin.codegen.optimization.common.FastMethodAnalyzer$$Lambda$1677/0x00007147129f7de0.invoke(Unknown Source)
	at org.jetbrains.kotlin.codegen.optimization.common.FastAnalyzer.fullMergeControlFlowEdge(FastAnalyzer.kt:233)
	at org.jetbrains.kotlin.codegen.optimization.common.FastAnalyzer.mergeControlFlowEdge(FastAnalyzer.kt:216)
	at org.jetbrains.kotlin.codegen.optimization.common.FastAnalyzer.processControlFlowEdge(FastAnalyzer.kt:208)
	at org.jetbrains.kotlin.codegen.optimization.common.FastAnalyzer.processControlFlowEdge$default(FastAnalyzer.kt:206)
	at org.jetbrains.kotlin.codegen.optimization.common.FastAnalyzer.visitOpInsn(FastAnalyzer.kt:292)
	at org.jetbrains.kotlin.codegen.optimization.common.FastAnalyzer.visitMeaningfulInstruction(FastAnalyzer.kt:281)
	at org.jetbrains.kotlin.codegen.optimization.common.FastAnalyzer.analyzeInstruction(FastAnalyzer.kt:113)
	at org.jetbrains.kotlin.codegen.optimization.common.FastAnalyzer.analyzeMainLoop(FastAnalyzer.kt:74)
	at org.jetbrains.kotlin.codegen.optimization.common.FastAnalyzer.analyze(FastAnalyzer.kt:53)
	at org.jetbrains.kotlin.codegen.optimization.transformer.MethodTransformer.analyze(MethodTransformer.java:49)
	at org.jetbrains.kotlin.codegen.optimization.nullCheck.RedundantNullCheckMethodTransformer$TransformerPass.analyzeNullabilities(RedundantNullCheckMethodTransformer.kt:65)
	at org.jetbrains.kotlin.codegen.optimization.nullCheck.RedundantNullCheckMethodTransformer$TransformerPass.run(RedundantNullCheckMethodTransformer.kt:55)
	at org.jetbrains.kotlin.codegen.optimization.nullCheck.RedundantNullCheckMethodTransformer.transform(RedundantNullCheckMethodTransformer.kt:43)
	at org.jetbrains.kotlin.codegen.optimization.transformer.CompositeMethodTransformer.transform(CompositeMethodTransformer.kt:25)
	at org.jetbrains.kotlin.codegen.optimization.OptimizationMethodVisitor.performTransformations(OptimizationMethodVisitor.kt:74)
	at org.jetbrains.kotlin.codegen.TransformationMethodVisitor.visitEnd(TransformationMethodVisitor.kt:67)
	at org.jetbrains.org.objectweb.asm.MethodVisitor.visitEnd(MethodVisitor.java:783)
	at org.jetbrains.org.objectweb.asm.tree.MethodNode.accept(MethodNode.java:772)
	at org.jetbrains.kotlin.backend.jvm.codegen.ClassCodegen.generateMethod(ClassCodegen.kt:453)
	at org.jetbrains.kotlin.backend.jvm.codegen.ClassCodegen.generate(ClassCodegen.kt:168)
	at org.jetbrains.kotlin.backend.jvm.FileCodegen.lower(JvmPhases.kt:39)
	at org.jetbrains.kotlin.backend.common.phaser.PhaseFactoriesKt.createFilePhase$lambda$4(PhaseFactories.kt:71)
	at org.jetbrains.kotlin.backend.common.phaser.PhaseFactoriesKt$$Lambda$165/0x0000714712123720.invoke(Unknown Source)
	at org.jetbrains.kotlin.backend.common.phaser.PhaseBuildersKt$createSimpleNamedCompilerPhase$1.phaseBody(PhaseBuilders.kt:69)
	at org.jetbrains.kotlin.backend.common.phaser.SimpleNamedCompilerPhase.phaseBody(CompilerPhase.kt:226)
	at org.jetbrains.kotlin.backend.common.phaser.AbstractNamedCompilerPhase.invoke(CompilerPhase.kt:113)
	at org.jetbrains.kotlin.backend.common.phaser.PerformByIrFilePhase.invokeSequential(performByIrFile.kt:62)
	at org.jetbrains.kotlin.backend.common.phaser.PerformByIrFilePhase.invoke(performByIrFile.kt:52)
	at org.jetbrains.kotlin.backend.common.phaser.PerformByIrFilePhase.invoke(performByIrFile.kt:38)


