kotlin version: 2.0.21
error message: org.jetbrains.kotlin.codegen.CompilationException: Back-end (JVM) Internal error: Couldn't transform method node:
UnifiedBlockingScreenSimple$loadDataFunction (Lcom/hieltech/haramblur/detection/AppBlockingManager;Lcom/hieltech/haramblur/detection/EnhancedSiteBlockingManager;Landroidx/compose/material3/SnackbarHostState;Landroidx/compose/runtime/MutableState;Landroidx/compose/runtime/MutableIntState;Landroidx/compose/runtime/MutableState;Landroidx/compose/runtime/MutableState;Landroidx/compose/runtime/MutableState;Landroidx/compose/runtime/MutableState;Landroidx/compose/runtime/MutableState;Lkotlin/coroutines/Continuation;)Ljava/lang/Object;:
    // annotable parameter count: 11 (visible)
    // annotable parameter count: 11 (invisible)
    TRYCATCHBLOCK L0 L1 L2 java/lang/Exception
    TRYCATCHBLOCK L3 L4 L2 java/lang/Exception
    TRYCATCHBLOCK L5 L6 L2 java/lang/Exception
    TRYCATCHBLOCK L7 L8 L2 java/lang/Exception
    TRYCATCHBLOCK L9 L10 L2 java/lang/Exception
    TRYCATCHBLOCK L0 L1 L11 null
    TRYCATCHBLOCK L3 L4 L11 null
    TRYCATCHBLOCK L5 L6 L11 null
    TRYCATCHBLOCK L7 L8 L11 null
    TRYCATCHBLOCK L9 L12 L11 null
    TRYCATCHBLOCK L13 L14 L11 null
    TRYCATCHBLOCK L15 L16 L11 null
    TRYCATCHBLOCK L17 L18 L11 null
   L19
    ALOAD 10
    INSTANCEOF com/hieltech/haramblur/ui/UnifiedBlockingScreenResponsiveKt$UnifiedBlockingScreenSimple$loadDataFunction$1
    IFEQ L20
    ALOAD 10
    CHECKCAST com/hieltech/haramblur/ui/UnifiedBlockingScreenResponsiveKt$UnifiedBlockingScreenSimple$loadDataFunction$1
    ASTORE 17
    ALOAD 17
    GETFIELD com/hieltech/haramblur/ui/UnifiedBlockingScreenResponsiveKt$UnifiedBlockingScreenSimple$loadDataFunction$1.label : I
    LDC -2147483648
    IAND
    IFEQ L20
    ALOAD 17
    DUP
    GETFIELD com/hieltech/haramblur/ui/UnifiedBlockingScreenResponsiveKt$UnifiedBlockingScreenSimple$loadDataFunction$1.label : I
    LDC -2147483648
    ISUB
    PUTFIELD com/hieltech/haramblur/ui/UnifiedBlockingScreenResponsiveKt$UnifiedBlockingScreenSimple$loadDataFunction$1.label : I
    GOTO L21
   L20
    NEW com/hieltech/haramblur/ui/UnifiedBlockingScreenResponsiveKt$UnifiedBlockingScreenSimple$loadDataFunction$1
    DUP
    ALOAD 10
    INVOKESPECIAL com/hieltech/haramblur/ui/UnifiedBlockingScreenResponsiveKt$UnifiedBlockingScreenSimple$loadDataFunction$1.<init> (Lkotlin/coroutines/Continuation;)V
    ASTORE 17
   L21
    ALOAD 17
    GETFIELD com/hieltech/haramblur/ui/UnifiedBlockingScreenResponsiveKt$UnifiedBlockingScreenSimple$loadDataFunction$1.result : Ljava/lang/Object;
    ASTORE 16
   L22
    INVOKESTATIC kotlin/coroutines/intrinsics/IntrinsicsKt.getCOROUTINE_SUSPENDED ()Ljava/lang/Object;
   L23
    LINENUMBER 110 L23
    ASTORE 18
    ALOAD 17
    GETFIELD com/hieltech/haramblur/ui/UnifiedBlockingScreenResponsiveKt$UnifiedBlockingScreenSimple$loadDataFunction$1.label : I
    TABLESWITCH
      0: L24
      1: L25
      2: L26
      3: L27
      4: L28
      5: L29
      default: L30
   L24
    ALOAD 16
    INVOKESTATIC kotlin/ResultKt.throwOnFailure (Ljava/lang/Object;)V
   L31
   L32
    LINENUMBER 111 L32
    ALOAD 3
    INVOKESTATIC com/hieltech/haramblur/ui/UnifiedBlockingScreenResponsiveKt.UnifiedBlockingScreenSimple$lambda$8 (Landroidx/compose/runtime/MutableState;)Z
    IFEQ L33
    GETSTATIC kotlin/Unit.INSTANCE : Lkotlin/Unit;
    ARETURN
   L34
   L33
   L35
   L36
    LINENUMBER 113 L36
    ALOAD 3
    NOP
    ICONST_1
    INVOKESTATIC com/hieltech/haramblur/ui/UnifiedBlockingScreenResponsiveKt.UnifiedBlockingScreenSimple$lambda$9 (Landroidx/compose/runtime/MutableState;Z)V
   L37
    LINENUMBER 114 L37
   L38
   L0
    NOP
   L39
    LINENUMBER 116 L39
    ALOAD 4
    INVOKESTATIC com/hieltech/haramblur/ui/UnifiedBlockingScreenResponsiveKt.UnifiedBlockingScreenSimple$lambda$5 (Landroidx/compose/runtime/MutableIntState;)I
    ISTORE 11
   L40
    ILOAD 11
    TABLESWITCH
      0: L41
      1: L42
      default: L43
   L41
   L44
    LINENUMBER 119 L44
    ALOAD 0
    IFNULL L45
    ALOAD 0
    ALOAD 17
    ALOAD 17
    ALOAD 0
    PUTFIELD com/hieltech/haramblur/ui/UnifiedBlockingScreenResponsiveKt$UnifiedBlockingScreenSimple$loadDataFunction$1.L$0 : Ljava/lang/Object;
    ALOAD 17
    ALOAD 2
    PUTFIELD com/hieltech/haramblur/ui/UnifiedBlockingScreenResponsiveKt$UnifiedBlockingScreenSimple$loadDataFunction$1.L$1 : Ljava/lang/Object;
    ALOAD 17
    ALOAD 3
    PUTFIELD com/hieltech/haramblur/ui/UnifiedBlockingScreenResponsiveKt$UnifiedBlockingScreenSimple$loadDataFunction$1.L$2 : Ljava/lang/Object;
    ALOAD 17
    ALOAD 5
    PUTFIELD com/hieltech/haramblur/ui/UnifiedBlockingScreenResponsiveKt$UnifiedBlockingScreenSimple$loadDataFunction$1.L$3 : Ljava/lang/Object;
    ALOAD 17
    ALOAD 6
    PUTFIELD com/hieltech/haramblur/ui/UnifiedBlockingScreenResponsiveKt$UnifiedBlockingScreenSimple$loadDataFunction$1.L$4 : Ljava/lang/Object;
    ALOAD 17
    ALOAD 7
    PUTFIELD com/hieltech/haramblur/ui/UnifiedBlockingScreenResponsiveKt$UnifiedBlockingScreenSimple$loadDataFunction$1.L$5 : Ljava/lang/Object;
    ALOAD 17
    ALOAD 9
    PUTFIELD com/hieltech/haramblur/ui/UnifiedBlockingScreenResponsiveKt$UnifiedBlockingScreenSimple$loadDataFunction$1.L$6 : Ljava/lang/Object;
    ALOAD 17
    ICONST_1
    PUTFIELD com/hieltech/haramblur/ui/UnifiedBlockingScreenResponsiveKt$UnifiedBlockingScreenSimple$loadDataFunction$1.label : I
    INVOKEINTERFACE com/hieltech/haramblur/detection/AppBlockingManager.getInstalledApps (Lkotlin/coroutines/Continuation;)Ljava/lang/Object; (itf)
   L1
    DUP
    ALOAD 18
    IF_ACMPNE L46
   L47
    LINENUMBER 110 L47
    ALOAD 18
    ARETURN
   L25
    ALOAD 17
    GETFIELD com/hieltech/haramblur/ui/UnifiedBlockingScreenResponsiveKt$UnifiedBlockingScreenSimple$loadDataFunction$1.L$6 : Ljava/lang/Object;
    CHECKCAST androidx/compose/runtime/MutableState
    ASTORE 9
   L48
    ALOAD 17
    GETFIELD com/hieltech/haramblur/ui/UnifiedBlockingScreenResponsiveKt$UnifiedBlockingScreenSimple$loadDataFunction$1.L$5 : Ljava/lang/Object;
    CHECKCAST androidx/compose/runtime/MutableState
    ASTORE 7
   L49
    ALOAD 17
    GETFIELD com/hieltech/haramblur/ui/UnifiedBlockingScreenResponsiveKt$UnifiedBlockingScreenSimple$loadDataFunction$1.L$4 : Ljava/lang/Object;
    CHECKCAST androidx/compose/runtime/MutableState
    ASTORE 6
   L50
    ALOAD 17
    GETFIELD com/hieltech/haramblur/ui/UnifiedBlockingScreenResponsiveKt$UnifiedBlockingScreenSimple$loadDataFunction$1.L$3 : Ljava/lang/Object;
    CHECKCAST androidx/compose/runtime/MutableState
    ASTORE 5
   L51
    ALOAD 17
    GETFIELD com/hieltech/haramblur/ui/UnifiedBlockingScreenResponsiveKt$UnifiedBlockingScreenSimple$loadDataFunction$1.L$2 : Ljava/lang/Object;
    CHECKCAST androidx/compose/runtime/MutableState
    ASTORE 3
   L52
    ALOAD 17
    GETFIELD com/hieltech/haramblur/ui/UnifiedBlockingScreenResponsiveKt$UnifiedBlockingScreenSimple$loadDataFunction$1.L$1 : Ljava/lang/Object;
    CHECKCAST androidx/compose/material3/SnackbarHostState
    ASTORE 2
   L53
    ALOAD 17
    GETFIELD com/hieltech/haramblur/ui/UnifiedBlockingScreenResponsiveKt$UnifiedBlockingScreenSimple$loadDataFunction$1.L$0 : Ljava/lang/Object;
    CHECKCAST com/hieltech/haramblur/detection/AppBlockingManager
    ASTORE 0
   L54
   L3
    NOP
    ALOAD 16
    INVOKESTATIC kotlin/ResultKt.throwOnFailure (Ljava/lang/Object;)V
    ALOAD 16
   L46
    LINENUMBER 119 L46
    CHECKCAST java/util/List
    ASTORE 13
   L55
    ALOAD 13
    IFNULL L45
    ALOAD 13
    GOTO L56
   L45
    NOP
    INVOKESTATIC kotlin/collections/CollectionsKt.emptyList ()Ljava/util/List;
   L56
   L57
    ASTORE 12
   L58
   L59
    LINENUMBER 120 L59
    ALOAD 5
    GETSTATIC com/hieltech/haramblur/utils/SocialMediaDetector.INSTANCE : Lcom/hieltech/haramblur/utils/SocialMediaDetector;
    ALOAD 12
    INVOKEVIRTUAL com/hieltech/haramblur/utils/SocialMediaDetector.getInstalledSocialMediaApps (Ljava/util/List;)Ljava/util/List;
    INVOKESTATIC com/hieltech/haramblur/ui/UnifiedBlockingScreenResponsiveKt.UnifiedBlockingScreenSimple$lambda$18 (Landroidx/compose/runtime/MutableState;Ljava/util/List;)V
   L60
    LINENUMBER 121 L60
    ALOAD 6
    ALOAD 0
    IFNULL L61
    ASTORE 14
    ALOAD 0
    ALOAD 17
    ALOAD 17
    ALOAD 0
    PUTFIELD com/hieltech/haramblur/ui/UnifiedBlockingScreenResponsiveKt$UnifiedBlockingScreenSimple$loadDataFunction$1.L$0 : Ljava/lang/Object;
    ALOAD 17
    ALOAD 2
    PUTFIELD com/hieltech/haramblur/ui/UnifiedBlockingScreenResponsiveKt$UnifiedBlockingScreenSimple$loadDataFunction$1.L$1 : Ljava/lang/Object;
    ALOAD 17
    ALOAD 3
    PUTFIELD com/hieltech/haramblur/ui/UnifiedBlockingScreenResponsiveKt$UnifiedBlockingScreenSimple$loadDataFunction$1.L$2 : Ljava/lang/Object;
    ALOAD 17
    ALOAD 7
    PUTFIELD com/hieltech/haramblur/ui/UnifiedBlockingScreenResponsiveKt$UnifiedBlockingScreenSimple$loadDataFunction$1.L$3 : Ljava/lang/Object;
    ALOAD 17
    ALOAD 9
    PUTFIELD com/hieltech/haramblur/ui/UnifiedBlockingScreenResponsiveKt$UnifiedBlockingScreenSimple$loadDataFunction$1.L$4 : Ljava/lang/Object;
    ALOAD 17
    ALOAD 14
    PUTFIELD com/hieltech/haramblur/ui/UnifiedBlockingScreenResponsiveKt$UnifiedBlockingScreenSimple$loadDataFunction$1.L$5 : Ljava/lang/Object;
    ALOAD 17
    ACONST_NULL
    PUTFIELD com/hieltech/haramblur/ui/UnifiedBlockingScreenResponsiveKt$UnifiedBlockingScreenSimple$loadDataFunction$1.L$6 : Ljava/lang/Object;
    ALOAD 17
    ICONST_2
    PUTFIELD com/hieltech/haramblur/ui/UnifiedBlockingScreenResponsiveKt$UnifiedBlockingScreenSimple$loadDataFunction$1.label : I
    INVOKEINTERFACE com/hieltech/haramblur/detection/AppBlockingManager.getBlockedApps (Lkotlin/coroutines/Continuation;)Ljava/lang/Object; (itf)
   L4
    DUP
    ALOAD 18
    IF_ACMPNE L62
   L63
    LINENUMBER 110 L63
    ALOAD 18
    ARETURN
   L26
    ALOAD 17
    GETFIELD com/hieltech/haramblur/ui/UnifiedBlockingScreenResponsiveKt$UnifiedBlockingScreenSimple$loadDataFunction$1.L$5 : Ljava/lang/Object;
    CHECKCAST androidx/compose/runtime/MutableState
    ASTORE 14
    ALOAD 17
    GETFIELD com/hieltech/haramblur/ui/UnifiedBlockingScreenResponsiveKt$UnifiedBlockingScreenSimple$loadDataFunction$1.L$4 : Ljava/lang/Object;
    CHECKCAST androidx/compose/runtime/MutableState
    ASTORE 9
   L64
    ALOAD 17
    GETFIELD com/hieltech/haramblur/ui/UnifiedBlockingScreenResponsiveKt$UnifiedBlockingScreenSimple$loadDataFunction$1.L$3 : Ljava/lang/Object;
    CHECKCAST androidx/compose/runtime/MutableState
    ASTORE 7
   L65
    ALOAD 17
    GETFIELD com/hieltech/haramblur/ui/UnifiedBlockingScreenResponsiveKt$UnifiedBlockingScreenSimple$loadDataFunction$1.L$2 : Ljava/lang/Object;
    CHECKCAST androidx/compose/runtime/MutableState
    ASTORE 3
   L66
    ALOAD 17
    GETFIELD com/hieltech/haramblur/ui/UnifiedBlockingScreenResponsiveKt$UnifiedBlockingScreenSimple$loadDataFunction$1.L$1 : Ljava/lang/Object;
    CHECKCAST androidx/compose/material3/SnackbarHostState
    ASTORE 2
   L67
    ALOAD 17
    GETFIELD com/hieltech/haramblur/ui/UnifiedBlockingScreenResponsiveKt$UnifiedBlockingScreenSimple$loadDataFunction$1.L$0 : Ljava/lang/Object;
    CHECKCAST com/hieltech/haramblur/detection/AppBlockingManager
    ASTORE 0
   L68
   L5
    NOP
    ALOAD 16
    INVOKESTATIC kotlin/ResultKt.throwOnFailure (Ljava/lang/Object;)V
    ALOAD 16
   L62
    LINENUMBER 121 L62
    ASTORE 15
    ALOAD 14
    ALOAD 15
    CHECKCAST java/util/List
    ASTORE 13
   L69
    ALOAD 13
    IFNULL L61
    ALOAD 13
    GOTO L70
   L61
    NOP
    INVOKESTATIC kotlin/collections/CollectionsKt.emptyList ()Ljava/util/List;
   L70
   L71
    INVOKESTATIC com/hieltech/haramblur/ui/UnifiedBlockingScreenResponsiveKt.UnifiedBlockingScreenSimple$lambda$21 (Landroidx/compose/runtime/MutableState;Ljava/util/List;)V
   L72
    LINENUMBER 122 L72
    ALOAD 7
    ALOAD 0
    IFNULL L73
    ASTORE 14
    ALOAD 0
    ALOAD 17
    ALOAD 17
    ALOAD 2
    PUTFIELD com/hieltech/haramblur/ui/UnifiedBlockingScreenResponsiveKt$UnifiedBlockingScreenSimple$loadDataFunction$1.L$0 : Ljava/lang/Object;
    ALOAD 17
    ALOAD 3
    PUTFIELD com/hieltech/haramblur/ui/UnifiedBlockingScreenResponsiveKt$UnifiedBlockingScreenSimple$loadDataFunction$1.L$1 : Ljava/lang/Object;
    ALOAD 17
    ALOAD 9
    PUTFIELD com/hieltech/haramblur/ui/UnifiedBlockingScreenResponsiveKt$UnifiedBlockingScreenSimple$loadDataFunction$1.L$2 : Ljava/lang/Object;
    ALOAD 17
    ALOAD 14
    PUTFIELD com/hieltech/haramblur/ui/UnifiedBlockingScreenResponsiveKt$UnifiedBlockingScreenSimple$loadDataFunction$1.L$3 : Ljava/lang/Object;
    ALOAD 17
    ACONST_NULL
    PUTFIELD com/hieltech/haramblur/ui/UnifiedBlockingScreenResponsiveKt$UnifiedBlockingScreenSimple$loadDataFunction$1.L$4 : Ljava/lang/Object;
    ALOAD 17
    ACONST_NULL
    PUTFIELD com/hieltech/haramblur/ui/UnifiedBlockingScreenResponsiveKt$UnifiedBlockingScreenSimple$loadDataFunction$1.L$5 : Ljava/lang/Object;
    ALOAD 17
    ACONST_NULL
    PUTFIELD com/hieltech/haramblur/ui/UnifiedBlockingScreenResponsiveKt$UnifiedBlockingScreenSimple$loadDataFunction$1.L$6 : Ljava/lang/Object;
    ALOAD 17
    ICONST_3
    PUTFIELD com/hieltech/haramblur/ui/UnifiedBlockingScreenResponsiveKt$UnifiedBlockingScreenSimple$loadDataFunction$1.label : I
    INVOKEINTERFACE com/hieltech/haramblur/detection/AppBlockingManager.getSocialMediaBlockingStats (Lkotlin/coroutines/Continuation;)Ljava/lang/Object; (itf)
   L6
    DUP
    ALOAD 18
    IF_ACMPNE L74
   L75
    LINENUMBER 110 L75
    ALOAD 18
    ARETURN
   L27
    ALOAD 17
    GETFIELD com/hieltech/haramblur/ui/UnifiedBlockingScreenResponsiveKt$UnifiedBlockingScreenSimple$loadDataFunction$1.L$3 : Ljava/lang/Object;
    CHECKCAST androidx/compose/runtime/MutableState
    ASTORE 14
    ALOAD 17
    GETFIELD com/hieltech/haramblur/ui/UnifiedBlockingScreenResponsiveKt$UnifiedBlockingScreenSimple$loadDataFunction$1.L$2 : Ljava/lang/Object;
    CHECKCAST androidx/compose/runtime/MutableState
    ASTORE 9
   L76
    ALOAD 17
    GETFIELD com/hieltech/haramblur/ui/UnifiedBlockingScreenResponsiveKt$UnifiedBlockingScreenSimple$loadDataFunction$1.L$1 : Ljava/lang/Object;
    CHECKCAST androidx/compose/runtime/MutableState
    ASTORE 3
   L77
    ALOAD 17
    GETFIELD com/hieltech/haramblur/ui/UnifiedBlockingScreenResponsiveKt$UnifiedBlockingScreenSimple$loadDataFunction$1.L$0 : Ljava/lang/Object;
    CHECKCAST androidx/compose/material3/SnackbarHostState
    ASTORE 2
   L78
   L7
    NOP
    ALOAD 16
    INVOKESTATIC kotlin/ResultKt.throwOnFailure (Ljava/lang/Object;)V
    ALOAD 16
   L74
    LINENUMBER 122 L74
    ASTORE 15
    ALOAD 14
    ALOAD 15
    CHECKCAST com/hieltech/haramblur/detection/AppBlockingManager$SocialMediaStats
    GOTO L79
   L73
    NOP
    ACONST_NULL
   L79
    INVOKESTATIC com/hieltech/haramblur/ui/UnifiedBlockingScreenResponsiveKt.UnifiedBlockingScreenSimple$lambda$27 (Landroidx/compose/runtime/MutableState;Lcom/hieltech/haramblur/detection/AppBlockingManager$SocialMediaStats;)V
   L80
    GOTO L81
   L42
   L82
    LINENUMBER 126 L82
    ALOAD 8
    ALOAD 1
    IFNULL L83
    ASTORE 14
    ALOAD 1
    ALOAD 17
    ALOAD 17
    ALOAD 2
    PUTFIELD com/hieltech/haramblur/ui/UnifiedBlockingScreenResponsiveKt$UnifiedBlockingScreenSimple$loadDataFunction$1.L$0 : Ljava/lang/Object;
    ALOAD 17
    ALOAD 3
    PUTFIELD com/hieltech/haramblur/ui/UnifiedBlockingScreenResponsiveKt$UnifiedBlockingScreenSimple$loadDataFunction$1.L$1 : Ljava/lang/Object;
    ALOAD 17
    ALOAD 9
    PUTFIELD com/hieltech/haramblur/ui/UnifiedBlockingScreenResponsiveKt$UnifiedBlockingScreenSimple$loadDataFunction$1.L$2 : Ljava/lang/Object;
    ALOAD 17
    ALOAD 14
    PUTFIELD com/hieltech/haramblur/ui/UnifiedBlockingScreenResponsiveKt$UnifiedBlockingScreenSimple$loadDataFunction$1.L$3 : Ljava/lang/Object;
    ALOAD 17
    ICONST_4
    PUTFIELD com/hieltech/haramblur/ui/UnifiedBlockingScreenResponsiveKt$UnifiedBlockingScreenSimple$loadDataFunction$1.label : I
    INVOKEVIRTUAL com/hieltech/haramblur/detection/EnhancedSiteBlockingManager.getCustomBlockedWebsites (Lkotlin/coroutines/Continuation;)Ljava/lang/Object;
   L8
    DUP
    ALOAD 18
    IF_ACMPNE L84
   L85
    LINENUMBER 110 L85
    ALOAD 18
    ARETURN
   L28
    ALOAD 17
    GETFIELD com/hieltech/haramblur/ui/UnifiedBlockingScreenResponsiveKt$UnifiedBlockingScreenSimple$loadDataFunction$1.L$3 : Ljava/lang/Object;
    CHECKCAST androidx/compose/runtime/MutableState
    ASTORE 14
    ALOAD 17
    GETFIELD com/hieltech/haramblur/ui/UnifiedBlockingScreenResponsiveKt$UnifiedBlockingScreenSimple$loadDataFunction$1.L$2 : Ljava/lang/Object;
    CHECKCAST androidx/compose/runtime/MutableState
    ASTORE 9
   L86
    ALOAD 17
    GETFIELD com/hieltech/haramblur/ui/UnifiedBlockingScreenResponsiveKt$UnifiedBlockingScreenSimple$loadDataFunction$1.L$1 : Ljava/lang/Object;
    CHECKCAST androidx/compose/runtime/MutableState
    ASTORE 3
   L87
    ALOAD 17
    GETFIELD com/hieltech/haramblur/ui/UnifiedBlockingScreenResponsiveKt$UnifiedBlockingScreenSimple$loadDataFunction$1.L$0 : Ljava/lang/Object;
    CHECKCAST androidx/compose/material3/SnackbarHostState
    ASTORE 2
   L88
   L9
    NOP
    ALOAD 16
    INVOKESTATIC kotlin/ResultKt.throwOnFailure (Ljava/lang/Object;)V
    ALOAD 16
   L84
    LINENUMBER 126 L84
    ASTORE 15
    ALOAD 14
    ALOAD 15
    CHECKCAST java/util/List
    ASTORE 12
   L89
    ALOAD 12
    IFNULL L83
    ALOAD 12
    GOTO L90
   L83
    NOP
    INVOKESTATIC kotlin/collections/CollectionsKt.emptyList ()Ljava/util/List;
   L90
   L91
    INVOKESTATIC com/hieltech/haramblur/ui/UnifiedBlockingScreenResponsiveKt.UnifiedBlockingScreenSimple$lambda$24 (Landroidx/compose/runtime/MutableState;Ljava/util/List;)V
    GOTO L81
   L43
   L81
   L92
   L93
    LINENUMBER 129 L93
    ALOAD 9
    NOP
    ICONST_1
    INVOKESTATIC com/hieltech/haramblur/ui/UnifiedBlockingScreenResponsiveKt.UnifiedBlockingScreenSimple$lambda$15 (Landroidx/compose/runtime/MutableState;Z)V
    GETSTATIC kotlin/Unit.INSTANCE : Lkotlin/Unit;
    ASTORE 11
   L10
   L12
   L94
    LINENUMBER 137 L94
    ALOAD 3
    NOP
    ICONST_0
    INVOKESTATIC com/hieltech/haramblur/ui/UnifiedBlockingScreenResponsiveKt.UnifiedBlockingScreenSimple$lambda$9 (Landroidx/compose/runtime/MutableState;Z)V
   L95
    LINENUMBER 138 L95
    GOTO L96
   L13
   L2
   L97
    LINENUMBER 130 L97
    ASTORE 12
   L98
   L99
    LINENUMBER 132 L99
    ALOAD 2
   L100
    LINENUMBER 133 L100
    LDC "Failed to load data"
   L101
    LINENUMBER 132 L101
    ACONST_NULL
    NOP
    ICONST_0
   L102
    LINENUMBER 134 L102
    GETSTATIC androidx/compose/material3/SnackbarDuration.Short : Landroidx/compose/material3/SnackbarDuration;
    ALOAD 17
   L103
    LINENUMBER 132 L103
    BIPUSH 6
    ACONST_NULL
    ALOAD 17
    ALOAD 3
    PUTFIELD com/hieltech/haramblur/ui/UnifiedBlockingScreenResponsiveKt$UnifiedBlockingScreenSimple$loadDataFunction$1.L$0 : Ljava/lang/Object;
    ALOAD 17
    ACONST_NULL
    PUTFIELD com/hieltech/haramblur/ui/UnifiedBlockingScreenResponsiveKt$UnifiedBlockingScreenSimple$loadDataFunction$1.L$1 : Ljava/lang/Object;
    ALOAD 17
    ACONST_NULL
    PUTFIELD com/hieltech/haramblur/ui/UnifiedBlockingScreenResponsiveKt$UnifiedBlockingScreenSimple$loadDataFunction$1.L$2 : Ljava/lang/Object;
    ALOAD 17
    ACONST_NULL
    PUTFIELD com/hieltech/haramblur/ui/UnifiedBlockingScreenResponsiveKt$UnifiedBlockingScreenSimple$loadDataFunction$1.L$3 : Ljava/lang/Object;
    ALOAD 17
    ACONST_NULL
    PUTFIELD com/hieltech/haramblur/ui/UnifiedBlockingScreenResponsiveKt$UnifiedBlockingScreenSimple$loadDataFunction$1.L$4 : Ljava/lang/Object;
    ALOAD 17
    ACONST_NULL
    PUTFIELD com/hieltech/haramblur/ui/UnifiedBlockingScreenResponsiveKt$UnifiedBlockingScreenSimple$loadDataFunction$1.L$5 : Ljava/lang/Object;
    ALOAD 17
    ACONST_NULL
    PUTFIELD com/hieltech/haramblur/ui/UnifiedBlockingScreenResponsiveKt$UnifiedBlockingScreenSimple$loadDataFunction$1.L$6 : Ljava/lang/Object;
    ALOAD 17
    ICONST_5
    PUTFIELD com/hieltech/haramblur/ui/UnifiedBlockingScreenResponsiveKt$UnifiedBlockingScreenSimple$loadDataFunction$1.label : I
    INVOKESTATIC androidx/compose/material3/SnackbarHostState.showSnackbar$default (Landroidx/compose/material3/SnackbarHostState;Ljava/lang/String;Ljava/lang/String;ZLandroidx/compose/material3/SnackbarDuration;Lkotlin/coroutines/Continuation;ILjava/lang/Object;)Ljava/lang/Object;
   L14
    DUP
    ALOAD 18
    IF_ACMPNE L104
   L105
    LINENUMBER 110 L105
    ALOAD 18
    ARETURN
   L29
    ALOAD 17
    GETFIELD com/hieltech/haramblur/ui/UnifiedBlockingScreenResponsiveKt$UnifiedBlockingScreenSimple$loadDataFunction$1.L$0 : Ljava/lang/Object;
    CHECKCAST androidx/compose/runtime/MutableState
    ASTORE 3
   L106
   L15
    NOP
    ALOAD 16
    INVOKESTATIC kotlin/ResultKt.throwOnFailure (Ljava/lang/Object;)V
    ALOAD 16
   L104
    ASTORE 11
   L107
   L16
   L108
    LINENUMBER 137 L108
    ALOAD 3
    NOP
    ICONST_0
    INVOKESTATIC com/hieltech/haramblur/ui/UnifiedBlockingScreenResponsiveKt.UnifiedBlockingScreenSimple$lambda$9 (Landroidx/compose/runtime/MutableState;Z)V
   L109
    LINENUMBER 138 L109
    GOTO L96
   L17
   L11
   L110
    LINENUMBER 137 L110
    ASTORE 12
   L18
   L111
    ALOAD 3
    NOP
    ICONST_0
    INVOKESTATIC com/hieltech/haramblur/ui/UnifiedBlockingScreenResponsiveKt.UnifiedBlockingScreenSimple$lambda$9 (Landroidx/compose/runtime/MutableState;Z)V
   L112
    ALOAD 12
    ATHROW
   L96
   L113
    LINENUMBER 139 L113
    NOP
    GETSTATIC kotlin/Unit.INSTANCE : Lkotlin/Unit;
    ARETURN
   L114
   L115
   L30
    LINENUMBER 110 L30
    NEW java/lang/IllegalStateException
    DUP
    LDC "call to 'resume' before 'invoke' with coroutine"
    INVOKESPECIAL java/lang/IllegalStateException.<init> (Ljava/lang/String;)V
    ATHROW
    RETURN
   L116
    LOCALVARIABLE $appBlockingManager Lcom/hieltech/haramblur/detection/AppBlockingManager; L31 L25 0
    LOCALVARIABLE $appBlockingManager Lcom/hieltech/haramblur/detection/AppBlockingManager; L54 L26 0
    LOCALVARIABLE $appBlockingManager Lcom/hieltech/haramblur/detection/AppBlockingManager; L68 L6 0
    LOCALVARIABLE $siteBlockingManager Lcom/hieltech/haramblur/detection/EnhancedSiteBlockingManager; L31 L34 1
    LOCALVARIABLE $siteBlockingManager Lcom/hieltech/haramblur/detection/EnhancedSiteBlockingManager; L34 L41 1
    LOCALVARIABLE $siteBlockingManager Lcom/hieltech/haramblur/detection/EnhancedSiteBlockingManager; L42 L8 1
    LOCALVARIABLE snackbarHostState Landroidx/compose/material3/SnackbarHostState; L31 L25 2
    LOCALVARIABLE snackbarHostState Landroidx/compose/material3/SnackbarHostState; L53 L26 2
    LOCALVARIABLE snackbarHostState Landroidx/compose/material3/SnackbarHostState; L67 L27 2
    LOCALVARIABLE snackbarHostState Landroidx/compose/material3/SnackbarHostState; L78 L28 2
    LOCALVARIABLE snackbarHostState Landroidx/compose/material3/SnackbarHostState; L88 L10 2
    LOCALVARIABLE snackbarHostState Landroidx/compose/material3/SnackbarHostState; L13 L100 2
    LOCALVARIABLE isLoading$delegate Landroidx/compose/runtime/MutableState; L31 L25 3
    LOCALVARIABLE isLoading$delegate Landroidx/compose/runtime/MutableState; L52 L26 3
    LOCALVARIABLE isLoading$delegate Landroidx/compose/runtime/MutableState; L66 L27 3
    LOCALVARIABLE isLoading$delegate Landroidx/compose/runtime/MutableState; L77 L28 3
    LOCALVARIABLE isLoading$delegate Landroidx/compose/runtime/MutableState; L87 L95 3
    LOCALVARIABLE isLoading$delegate Landroidx/compose/runtime/MutableState; L13 L29 3
    LOCALVARIABLE isLoading$delegate Landroidx/compose/runtime/MutableState; L106 L109 3
    LOCALVARIABLE isLoading$delegate Landroidx/compose/runtime/MutableState; L17 L112 3
    LOCALVARIABLE selectedTab$delegate Landroidx/compose/runtime/MutableIntState; L31 L34 4
    LOCALVARIABLE selectedTab$delegate Landroidx/compose/runtime/MutableIntState; L34 L40 4
    LOCALVARIABLE socialMediaApps$delegate Landroidx/compose/runtime/MutableState; L31 L25 5
    LOCALVARIABLE socialMediaApps$delegate Landroidx/compose/runtime/MutableState; L51 L60 5
    LOCALVARIABLE blockedApps$delegate Landroidx/compose/runtime/MutableState; L31 L25 6
    LOCALVARIABLE blockedApps$delegate Landroidx/compose/runtime/MutableState; L50 L4 6
    LOCALVARIABLE socialMediaStats$delegate Landroidx/compose/runtime/MutableState; L31 L25 7
    LOCALVARIABLE socialMediaStats$delegate Landroidx/compose/runtime/MutableState; L49 L26 7
    LOCALVARIABLE socialMediaStats$delegate Landroidx/compose/runtime/MutableState; L65 L6 7
    LOCALVARIABLE customBlockedSites$delegate Landroidx/compose/runtime/MutableState; L31 L34 8
    LOCALVARIABLE customBlockedSites$delegate Landroidx/compose/runtime/MutableState; L34 L41 8
    LOCALVARIABLE customBlockedSites$delegate Landroidx/compose/runtime/MutableState; L42 L8 8
    LOCALVARIABLE dataLoaded$delegate Landroidx/compose/runtime/MutableState; L31 L25 9
    LOCALVARIABLE dataLoaded$delegate Landroidx/compose/runtime/MutableState; L48 L26 9
    LOCALVARIABLE dataLoaded$delegate Landroidx/compose/runtime/MutableState; L64 L27 9
    LOCALVARIABLE dataLoaded$delegate Landroidx/compose/runtime/MutableState; L76 L28 9
    LOCALVARIABLE dataLoaded$delegate Landroidx/compose/runtime/MutableState; L86 L10 9
    LOCALVARIABLE installedApps Ljava/util/List; L58 L60 12
    LOCALVARIABLE $completion Lkotlin/coroutines/Continuation; L19 L116 10
    LOCALVARIABLE $continuation Lkotlin/coroutines/Continuation; L21 L115 17
    LOCALVARIABLE $result Ljava/lang/Object; L22 L115 16
    MAXSTACK = 9
    MAXLOCALS = 19

File is unknown
The root cause org.jetbrains.kotlin.codegen.CompilationException was thrown at: org.jetbrains.kotlin.codegen.TransformationMethodVisitor.visitEnd(TransformationMethodVisitor.kt:89)
	at org.jetbrains.kotlin.codegen.TransformationMethodVisitor.visitEnd(TransformationMethodVisitor.kt:89)
	at org.jetbrains.org.objectweb.asm.tree.MethodNode.accept(MethodNode.java:772)
	at org.jetbrains.kotlin.backend.jvm.codegen.CoroutineCodegenKt.acceptWithStateMachine(CoroutineCodegen.kt:76)
	at org.jetbrains.kotlin.backend.jvm.codegen.ClassCodegen.generateMethod(ClassCodegen.kt:440)
	at org.jetbrains.kotlin.backend.jvm.codegen.ClassCodegen.generate(ClassCodegen.kt:168)
	at org.jetbrains.kotlin.backend.jvm.FileCodegen.lower(JvmPhases.kt:39)
	at org.jetbrains.kotlin.backend.common.phaser.PhaseFactoriesKt.createFilePhase$lambda$4(PhaseFactories.kt:71)
	at org.jetbrains.kotlin.backend.common.phaser.PhaseBuildersKt$createSimpleNamedCompilerPhase$1.phaseBody(PhaseBuilders.kt:69)
	at org.jetbrains.kotlin.backend.common.phaser.SimpleNamedCompilerPhase.phaseBody(CompilerPhase.kt:226)
	at org.jetbrains.kotlin.backend.common.phaser.AbstractNamedCompilerPhase.invoke(CompilerPhase.kt:113)
	at org.jetbrains.kotlin.backend.common.phaser.PerformByIrFilePhase.invokeSequential(performByIrFile.kt:62)
	at org.jetbrains.kotlin.backend.common.phaser.PerformByIrFilePhase.invoke(performByIrFile.kt:52)
	at org.jetbrains.kotlin.backend.common.phaser.PerformByIrFilePhase.invoke(performByIrFile.kt:38)
	at org.jetbrains.kotlin.backend.common.phaser.NamedCompilerPhase.phaseBody(CompilerPhase.kt:166)
	at org.jetbrains.kotlin.backend.common.phaser.AbstractNamedCompilerPhase.invoke(CompilerPhase.kt:113)
	at org.jetbrains.kotlin.backend.common.phaser.CompositePhase.invoke(PhaseBuilders.kt:27)
	at org.jetbrains.kotlin.backend.common.phaser.CompositePhase.invoke(PhaseBuilders.kt:14)
	at org.jetbrains.kotlin.backend.common.phaser.NamedCompilerPhase.phaseBody(CompilerPhase.kt:166)
	at org.jetbrains.kotlin.backend.common.phaser.AbstractNamedCompilerPhase.invoke(CompilerPhase.kt:113)
	at org.jetbrains.kotlin.backend.common.phaser.CompilerPhaseKt.invokeToplevel(CompilerPhase.kt:62)
	at org.jetbrains.kotlin.backend.jvm.JvmIrCodegenFactory.invokeCodegen(JvmIrCodegenFactory.kt:371)
	at org.jetbrains.kotlin.codegen.CodegenFactory.generateModule(CodegenFactory.kt:47)
	at org.jetbrains.kotlin.backend.jvm.JvmIrCodegenFactory.generateModuleInFrontendIRMode(JvmIrCodegenFactory.kt:433)
	at org.jetbrains.kotlin.cli.jvm.compiler.pipeline.JvmCompilerPipelineKt.generateCodeFromIr(jvmCompilerPipeline.kt:246)
	at org.jetbrains.kotlin.cli.jvm.compiler.pipeline.JvmCompilerPipelineKt.compileModulesUsingFrontendIrAndLightTree(jvmCompilerPipeline.kt:142)
	at org.jetbrains.kotlin.cli.jvm.K2JVMCompiler.doExecute(K2JVMCompiler.kt:148)
	at org.jetbrains.kotlin.cli.jvm.K2JVMCompiler.doExecute(K2JVMCompiler.kt:43)
	at org.jetbrains.kotlin.cli.common.CLICompiler.execImpl(CLICompiler.kt:103)
	at org.jetbrains.kotlin.cli.common.CLICompiler.execImpl(CLICompiler.kt:49)
	at org.jetbrains.kotlin.cli.common.CLITool.exec(CLITool.kt:101)
	at org.jetbrains.kotlin.incremental.IncrementalJvmCompilerRunner.runCompiler(IncrementalJvmCompilerRunner.kt:464)
	at org.jetbrains.kotlin.incremental.IncrementalJvmCompilerRunner.runCompiler(IncrementalJvmCompilerRunner.kt:73)
	at org.jetbrains.kotlin.incremental.IncrementalCompilerRunner.doCompile(IncrementalCompilerRunner.kt:506)
	at org.jetbrains.kotlin.incremental.IncrementalCompilerRunner.compileImpl(IncrementalCompilerRunner.kt:423)
	at org.jetbrains.kotlin.incremental.IncrementalCompilerRunner.compileNonIncrementally(IncrementalCompilerRunner.kt:301)
	at org.jetbrains.kotlin.incremental.IncrementalCompilerRunner.compile(IncrementalCompilerRunner.kt:129)
	at org.jetbrains.kotlin.daemon.CompileServiceImplBase.execIncrementalCompiler(CompileServiceImpl.kt:675)
	at org.jetbrains.kotlin.daemon.CompileServiceImplBase.access$execIncrementalCompiler(CompileServiceImpl.kt:92)
	at org.jetbrains.kotlin.daemon.CompileServiceImpl.compile(CompileServiceImpl.kt:1660)
	at jdk.internal.reflect.GeneratedMethodAccessor91.invoke(Unknown Source)
	at java.base/jdk.internal.reflect.DelegatingMethodAccessorImpl.invoke(DelegatingMethodAccessorImpl.java:43)
	at java.base/java.lang.reflect.Method.invoke(Method.java:569)
	at java.rmi/sun.rmi.server.UnicastServerRef.dispatch(UnicastServerRef.java:360)
	at java.rmi/sun.rmi.transport.Transport$1.run(Transport.java:200)
	at java.rmi/sun.rmi.transport.Transport$1.run(Transport.java:197)
	at java.base/java.security.AccessController.doPrivileged(AccessController.java:712)
	at java.rmi/sun.rmi.transport.Transport.serviceCall(Transport.java:196)
	at java.rmi/sun.rmi.transport.tcp.TCPTransport.handleMessages(TCPTransport.java:587)
	at java.rmi/sun.rmi.transport.tcp.TCPTransport$ConnectionHandler.run0(TCPTransport.java:828)
	at java.rmi/sun.rmi.transport.tcp.TCPTransport$ConnectionHandler.lambda$run$0(TCPTransport.java:705)
	at java.base/java.security.AccessController.doPrivileged(AccessController.java:399)
	at java.rmi/sun.rmi.transport.tcp.TCPTransport$ConnectionHandler.run(TCPTransport.java:704)
	at java.base/java.util.concurrent.ThreadPoolExecutor.runWorker(ThreadPoolExecutor.java:1136)
	at java.base/java.util.concurrent.ThreadPoolExecutor$Worker.run(ThreadPoolExecutor.java:635)
	at java.base/java.lang.Thread.run(Thread.java:840)
Caused by: org.jetbrains.kotlin.codegen.CompilationException: Back-end (JVM) Internal error: Couldn't transform method node:
UnifiedBlockingScreenSimple$loadDataFunction (Lcom/hieltech/haramblur/detection/AppBlockingManager;Lcom/hieltech/haramblur/detection/EnhancedSiteBlockingManager;Landroidx/compose/material3/SnackbarHostState;Landroidx/compose/runtime/MutableState;Landroidx/compose/runtime/MutableIntState;Landroidx/compose/runtime/MutableState;Landroidx/compose/runtime/MutableState;Landroidx/compose/runtime/MutableState;Landroidx/compose/runtime/MutableState;Landroidx/compose/runtime/MutableState;Lkotlin/coroutines/Continuation;)Ljava/lang/Object;:
    // annotable parameter count: 11 (visible)
    // annotable parameter count: 11 (invisible)
    TRYCATCHBLOCK L0 L1 L2 java/lang/Exception
    TRYCATCHBLOCK L3 L4 L2 java/lang/Exception
    TRYCATCHBLOCK L5 L6 L2 java/lang/Exception
    TRYCATCHBLOCK L7 L8 L2 java/lang/Exception
    TRYCATCHBLOCK L9 L10 L2 java/lang/Exception
    TRYCATCHBLOCK L0 L1 L11 null
    TRYCATCHBLOCK L3 L4 L11 null
    TRYCATCHBLOCK L5 L6 L11 null
    TRYCATCHBLOCK L7 L8 L11 null
    TRYCATCHBLOCK L9 L10 L11 null
    TRYCATCHBLOCK L2 L12 L11 null
    TRYCATCHBLOCK L13 L14 L11 null
    TRYCATCHBLOCK L11 L15 L11 null
   L16
    ALOAD 10
    INSTANCEOF com/hieltech/haramblur/ui/UnifiedBlockingScreenResponsiveKt$UnifiedBlockingScreenSimple$loadDataFunction$1
    IFEQ L17
    ALOAD 10
    CHECKCAST com/hieltech/haramblur/ui/UnifiedBlockingScreenResponsiveKt$UnifiedBlockingScreenSimple$loadDataFunction$1
    ASTORE 17
    ALOAD 17
    GETFIELD com/hieltech/haramblur/ui/UnifiedBlockingScreenResponsiveKt$UnifiedBlockingScreenSimple$loadDataFunction$1.label : I
    LDC -2147483648
    IAND
    IFEQ L17
    ALOAD 17
    DUP
    GETFIELD com/hieltech/haramblur/ui/UnifiedBlockingScreenResponsiveKt$UnifiedBlockingScreenSimple$loadDataFunction$1.label : I
    LDC -2147483648
    ISUB
    PUTFIELD com/hieltech/haramblur/ui/UnifiedBlockingScreenResponsiveKt$UnifiedBlockingScreenSimple$loadDataFunction$1.label : I
    GOTO L18
   L17
    NEW com/hieltech/haramblur/ui/UnifiedBlockingScreenResponsiveKt$UnifiedBlockingScreenSimple$loadDataFunction$1
    DUP
    ALOAD 10
    INVOKESPECIAL com/hieltech/haramblur/ui/UnifiedBlockingScreenResponsiveKt$UnifiedBlockingScreenSimple$loadDataFunction$1.<init> (Lkotlin/coroutines/Continuation;)V
    ASTORE 17
   L18
    ALOAD 17
    GETFIELD com/hieltech/haramblur/ui/UnifiedBlockingScreenResponsiveKt$UnifiedBlockingScreenSimple$loadDataFunction$1.result : Ljava/lang/Object;
    ASTORE 16
   L19
    INVOKESTATIC kotlin/coroutines/intrinsics/IntrinsicsKt.getCOROUTINE_SUSPENDED ()Ljava/lang/Object;
   L20
    LINENUMBER 110 L20
    ASTORE 18
    ALOAD 17
    GETFIELD com/hieltech/haramblur/ui/UnifiedBlockingScreenResponsiveKt$UnifiedBlockingScreenSimple$loadDataFunction$1.label : I
    TABLESWITCH
      0: L21
      1: L22
      2: L23
      3: L24
      4: L25
      5: L26
      default: L27
   L21
    ALOAD 16
    INVOKESTATIC kotlin/ResultKt.throwOnFailure (Ljava/lang/Object;)V
   L28
    LINENUMBER 111 L28
    ALOAD 3
    INVOKESTATIC com/hieltech/haramblur/ui/UnifiedBlockingScreenResponsiveKt.UnifiedBlockingScreenSimple$lambda$8 (Landroidx/compose/runtime/MutableState;)Z
    IFEQ L29
    GETSTATIC kotlin/Unit.INSTANCE : Lkotlin/Unit;
    ARETURN
   L29
    LINENUMBER 113 L29
    ALOAD 3
    ICONST_1
    INVOKESTATIC com/hieltech/haramblur/ui/UnifiedBlockingScreenResponsiveKt.UnifiedBlockingScreenSimple$lambda$9 (Landroidx/compose/runtime/MutableState;Z)V
   L30
    LINENUMBER 114 L30
   L0
    NOP
   L31
    LINENUMBER 116 L31
    ALOAD 4
    INVOKESTATIC com/hieltech/haramblur/ui/UnifiedBlockingScreenResponsiveKt.UnifiedBlockingScreenSimple$lambda$5 (Landroidx/compose/runtime/MutableIntState;)I
    ISTORE 11
   L32
    ILOAD 11
    TABLESWITCH
      0: L33
      1: L34
      default: L35
   L33
    LINENUMBER 119 L33
    ALOAD 0
    DUP
    IFNULL L36
    ALOAD 17
    ALOAD 17
    ALOAD 0
    PUTFIELD com/hieltech/haramblur/ui/UnifiedBlockingScreenResponsiveKt$UnifiedBlockingScreenSimple$loadDataFunction$1.L$0 : Ljava/lang/Object;
    ALOAD 17
    ALOAD 2
    PUTFIELD com/hieltech/haramblur/ui/UnifiedBlockingScreenResponsiveKt$UnifiedBlockingScreenSimple$loadDataFunction$1.L$1 : Ljava/lang/Object;
    ALOAD 17
    ALOAD 3
    PUTFIELD com/hieltech/haramblur/ui/UnifiedBlockingScreenResponsiveKt$UnifiedBlockingScreenSimple$loadDataFunction$1.L$2 : Ljava/lang/Object;
    ALOAD 17
    ALOAD 5
    PUTFIELD com/hieltech/haramblur/ui/UnifiedBlockingScreenResponsiveKt$UnifiedBlockingScreenSimple$loadDataFunction$1.L$3 : Ljava/lang/Object;
    ALOAD 17
    ALOAD 6
    PUTFIELD com/hieltech/haramblur/ui/UnifiedBlockingScreenResponsiveKt$UnifiedBlockingScreenSimple$loadDataFunction$1.L$4 : Ljava/lang/Object;
    ALOAD 17
    ALOAD 7
    PUTFIELD com/hieltech/haramblur/ui/UnifiedBlockingScreenResponsiveKt$UnifiedBlockingScreenSimple$loadDataFunction$1.L$5 : Ljava/lang/Object;
    ALOAD 17
    ALOAD 9
    PUTFIELD com/hieltech/haramblur/ui/UnifiedBlockingScreenResponsiveKt$UnifiedBlockingScreenSimple$loadDataFunction$1.L$6 : Ljava/lang/Object;
    ALOAD 17
    ICONST_1
    PUTFIELD com/hieltech/haramblur/ui/UnifiedBlockingScreenResponsiveKt$UnifiedBlockingScreenSimple$loadDataFunction$1.label : I
    INVOKEINTERFACE com/hieltech/haramblur/detection/AppBlockingManager.getInstalledApps (Lkotlin/coroutines/Continuation;)Ljava/lang/Object; (itf)
   L1
    DUP
    ALOAD 18
    IF_ACMPNE L37
   L38
    LINENUMBER 110 L38
    ALOAD 18
    ARETURN
   L22
    ALOAD 17
    GETFIELD com/hieltech/haramblur/ui/UnifiedBlockingScreenResponsiveKt$UnifiedBlockingScreenSimple$loadDataFunction$1.L$6 : Ljava/lang/Object;
    CHECKCAST androidx/compose/runtime/MutableState
    ASTORE 9
   L39
    ALOAD 17
    GETFIELD com/hieltech/haramblur/ui/UnifiedBlockingScreenResponsiveKt$UnifiedBlockingScreenSimple$loadDataFunction$1.L$5 : Ljava/lang/Object;
    CHECKCAST androidx/compose/runtime/MutableState
    ASTORE 7
   L40
    ALOAD 17
    GETFIELD com/hieltech/haramblur/ui/UnifiedBlockingScreenResponsiveKt$UnifiedBlockingScreenSimple$loadDataFunction$1.L$4 : Ljava/lang/Object;
    CHECKCAST androidx/compose/runtime/MutableState
    ASTORE 6
   L41
    ALOAD 17
    GETFIELD com/hieltech/haramblur/ui/UnifiedBlockingScreenResponsiveKt$UnifiedBlockingScreenSimple$loadDataFunction$1.L$3 : Ljava/lang/Object;
    CHECKCAST androidx/compose/runtime/MutableState
    ASTORE 5
   L42
    ALOAD 17
    GETFIELD com/hieltech/haramblur/ui/UnifiedBlockingScreenResponsiveKt$UnifiedBlockingScreenSimple$loadDataFunction$1.L$2 : Ljava/lang/Object;
    CHECKCAST androidx/compose/runtime/MutableState
    ASTORE 3
   L43
    ALOAD 17
    GETFIELD com/hieltech/haramblur/ui/UnifiedBlockingScreenResponsiveKt$UnifiedBlockingScreenSimple$loadDataFunction$1.L$1 : Ljava/lang/Object;
    CHECKCAST androidx/compose/material3/SnackbarHostState
    ASTORE 2
   L44
    ALOAD 17
    GETFIELD com/hieltech/haramblur/ui/UnifiedBlockingScreenResponsiveKt$UnifiedBlockingScreenSimple$loadDataFunction$1.L$0 : Ljava/lang/Object;
    CHECKCAST com/hieltech/haramblur/detection/AppBlockingManager
    ASTORE 0
   L3
    NOP
    ALOAD 16
    INVOKESTATIC kotlin/ResultKt.throwOnFailure (Ljava/lang/Object;)V
    ALOAD 16
   L37
    LINENUMBER 119 L37
    CHECKCAST java/util/List
    ASTORE 13
    ALOAD 13
    DUP
    IFNULL L36
    GOTO L45
   L36
    POP
    INVOKESTATIC kotlin/collections/CollectionsKt.emptyList ()Ljava/util/List;
   L45
    ASTORE 12
   L46
    LINENUMBER 120 L46
    ALOAD 5
    GETSTATIC com/hieltech/haramblur/utils/SocialMediaDetector.INSTANCE : Lcom/hieltech/haramblur/utils/SocialMediaDetector;
    ALOAD 12
    INVOKEVIRTUAL com/hieltech/haramblur/utils/SocialMediaDetector.getInstalledSocialMediaApps (Ljava/util/List;)Ljava/util/List;
    INVOKESTATIC com/hieltech/haramblur/ui/UnifiedBlockingScreenResponsiveKt.UnifiedBlockingScreenSimple$lambda$18 (Landroidx/compose/runtime/MutableState;Ljava/util/List;)V
   L47
    LINENUMBER 121 L47
    ALOAD 6
    ALOAD 0
    IFNULL L48
    ASTORE 14
    ALOAD 0
    ALOAD 17
    ALOAD 17
    ALOAD 0
    PUTFIELD com/hieltech/haramblur/ui/UnifiedBlockingScreenResponsiveKt$UnifiedBlockingScreenSimple$loadDataFunction$1.L$0 : Ljava/lang/Object;
    ALOAD 17
    ALOAD 2
    PUTFIELD com/hieltech/haramblur/ui/UnifiedBlockingScreenResponsiveKt$UnifiedBlockingScreenSimple$loadDataFunction$1.L$1 : Ljava/lang/Object;
    ALOAD 17
    ALOAD 3
    PUTFIELD com/hieltech/haramblur/ui/UnifiedBlockingScreenResponsiveKt$UnifiedBlockingScreenSimple$loadDataFunction$1.L$2 : Ljava/lang/Object;
    ALOAD 17
    ALOAD 7
    PUTFIELD com/hieltech/haramblur/ui/UnifiedBlockingScreenResponsiveKt$UnifiedBlockingScreenSimple$loadDataFunction$1.L$3 : Ljava/lang/Object;
    ALOAD 17
    ALOAD 9
    PUTFIELD com/hieltech/haramblur/ui/UnifiedBlockingScreenResponsiveKt$UnifiedBlockingScreenSimple$loadDataFunction$1.L$4 : Ljava/lang/Object;
    ALOAD 17
    ALOAD 14
    PUTFIELD com/hieltech/haramblur/ui/UnifiedBlockingScreenResponsiveKt$UnifiedBlockingScreenSimple$loadDataFunction$1.L$5 : Ljava/lang/Object;
    ALOAD 17
    ACONST_NULL
    PUTFIELD com/hieltech/haramblur/ui/UnifiedBlockingScreenResponsiveKt$UnifiedBlockingScreenSimple$loadDataFunction$1.L$6 : Ljava/lang/Object;
    ALOAD 17
    ICONST_2
    PUTFIELD com/hieltech/haramblur/ui/UnifiedBlockingScreenResponsiveKt$UnifiedBlockingScreenSimple$loadDataFunction$1.label : I
    INVOKEINTERFACE com/hieltech/haramblur/detection/AppBlockingManager.getBlockedApps (Lkotlin/coroutines/Continuation;)Ljava/lang/Object; (itf)
   L4
    DUP
    ALOAD 18
    IF_ACMPNE L49
   L50
    LINENUMBER 110 L50
    ALOAD 18
    ARETURN
   L23
    ALOAD 17
    GETFIELD com/hieltech/haramblur/ui/UnifiedBlockingScreenResponsiveKt$UnifiedBlockingScreenSimple$loadDataFunction$1.L$5 : Ljava/lang/Object;
    CHECKCAST androidx/compose/runtime/MutableState
    ASTORE 14
    ALOAD 17
    GETFIELD com/hieltech/haramblur/ui/UnifiedBlockingScreenResponsiveKt$UnifiedBlockingScreenSimple$loadDataFunction$1.L$4 : Ljava/lang/Object;
    CHECKCAST androidx/compose/runtime/MutableState
    ASTORE 9
   L51
    ALOAD 17
    GETFIELD com/hieltech/haramblur/ui/UnifiedBlockingScreenResponsiveKt$UnifiedBlockingScreenSimple$loadDataFunction$1.L$3 : Ljava/lang/Object;
    CHECKCAST androidx/compose/runtime/MutableState
    ASTORE 7
   L52
    ALOAD 17
    GETFIELD com/hieltech/haramblur/ui/UnifiedBlockingScreenResponsiveKt$UnifiedBlockingScreenSimple$loadDataFunction$1.L$2 : Ljava/lang/Object;
    CHECKCAST androidx/compose/runtime/MutableState
    ASTORE 3
   L53
    ALOAD 17
    GETFIELD com/hieltech/haramblur/ui/UnifiedBlockingScreenResponsiveKt$UnifiedBlockingScreenSimple$loadDataFunction$1.L$1 : Ljava/lang/Object;
    CHECKCAST androidx/compose/material3/SnackbarHostState
    ASTORE 2
   L54
    ALOAD 17
    GETFIELD com/hieltech/haramblur/ui/UnifiedBlockingScreenResponsiveKt$UnifiedBlockingScreenSimple$loadDataFunction$1.L$0 : Ljava/lang/Object;
    CHECKCAST com/hieltech/haramblur/detection/AppBlockingManager
    ASTORE 0
   L5
    NOP
    ALOAD 16
    INVOKESTATIC kotlin/ResultKt.throwOnFailure (Ljava/lang/Object;)V
    ALOAD 16
   L49
    LINENUMBER 121 L49
    ASTORE 15
    ALOAD 14
    ALOAD 15
    CHECKCAST java/util/List
    ASTORE 13
    ALOAD 13
    IFNULL L48
    ALOAD 13
    GOTO L55
   L48
    INVOKESTATIC kotlin/collections/CollectionsKt.emptyList ()Ljava/util/List;
   L55
    INVOKESTATIC com/hieltech/haramblur/ui/UnifiedBlockingScreenResponsiveKt.UnifiedBlockingScreenSimple$lambda$21 (Landroidx/compose/runtime/MutableState;Ljava/util/List;)V
   L56
    LINENUMBER 122 L56
    ALOAD 7
    ALOAD 0
    IFNULL L57
    ASTORE 14
    ALOAD 0
    ALOAD 17
    ALOAD 17
    ALOAD 2
    PUTFIELD com/hieltech/haramblur/ui/UnifiedBlockingScreenResponsiveKt$UnifiedBlockingScreenSimple$loadDataFunction$1.L$0 : Ljava/lang/Object;
    ALOAD 17
    ALOAD 3
    PUTFIELD com/hieltech/haramblur/ui/UnifiedBlockingScreenResponsiveKt$UnifiedBlockingScreenSimple$loadDataFunction$1.L$1 : Ljava/lang/Object;
    ALOAD 17
    ALOAD 9
    PUTFIELD com/hieltech/haramblur/ui/UnifiedBlockingScreenResponsiveKt$UnifiedBlockingScreenSimple$loadDataFunction$1.L$2 : Ljava/lang/Object;
    ALOAD 17
    ALOAD 14
    PUTFIELD com/hieltech/haramblur/ui/UnifiedBlockingScreenResponsiveKt$UnifiedBlockingScreenSimple$loadDataFunction$1.L$3 : Ljava/lang/Object;
    ALOAD 17
    ACONST_NULL
    PUTFIELD com/hieltech/haramblur/ui/UnifiedBlockingScreenResponsiveKt$UnifiedBlockingScreenSimple$loadDataFunction$1.L$4 : Ljava/lang/Object;
    ALOAD 17
    ACONST_NULL
    PUTFIELD com/hieltech/haramblur/ui/UnifiedBlockingScreenResponsiveKt$UnifiedBlockingScreenSimple$loadDataFunction$1.L$5 : Ljava/lang/Object;
    ALOAD 17
    ACONST_NULL
    PUTFIELD com/hieltech/haramblur/ui/UnifiedBlockingScreenResponsiveKt$UnifiedBlockingScreenSimple$loadDataFunction$1.L$6 : Ljava/lang/Object;
    ALOAD 17
    ICONST_3
    PUTFIELD com/hieltech/haramblur/ui/UnifiedBlockingScreenResponsiveKt$UnifiedBlockingScreenSimple$loadDataFunction$1.label : I
    INVOKEINTERFACE com/hieltech/haramblur/detection/AppBlockingManager.getSocialMediaBlockingStats (Lkotlin/coroutines/Continuation;)Ljava/lang/Object; (itf)
   L6
    DUP
    ALOAD 18
    IF_ACMPNE L58
   L59
    LINENUMBER 110 L59
    ALOAD 18
    ARETURN
   L24
    ALOAD 17
    GETFIELD com/hieltech/haramblur/ui/UnifiedBlockingScreenResponsiveKt$UnifiedBlockingScreenSimple$loadDataFunction$1.L$3 : Ljava/lang/Object;
    CHECKCAST androidx/compose/runtime/MutableState
    ASTORE 14
    ALOAD 17
    GETFIELD com/hieltech/haramblur/ui/UnifiedBlockingScreenResponsiveKt$UnifiedBlockingScreenSimple$loadDataFunction$1.L$2 : Ljava/lang/Object;
    CHECKCAST androidx/compose/runtime/MutableState
    ASTORE 9
   L60
    ALOAD 17
    GETFIELD com/hieltech/haramblur/ui/UnifiedBlockingScreenResponsiveKt$UnifiedBlockingScreenSimple$loadDataFunction$1.L$1 : Ljava/lang/Object;
    CHECKCAST androidx/compose/runtime/MutableState
    ASTORE 3
   L61
    ALOAD 17
    GETFIELD com/hieltech/haramblur/ui/UnifiedBlockingScreenResponsiveKt$UnifiedBlockingScreenSimple$loadDataFunction$1.L$0 : Ljava/lang/Object;
    CHECKCAST androidx/compose/material3/SnackbarHostState
    ASTORE 2
   L7
    NOP
    ALOAD 16
    INVOKESTATIC kotlin/ResultKt.throwOnFailure (Ljava/lang/Object;)V
    ALOAD 16
   L58
    LINENUMBER 122 L58
    ASTORE 15
    ALOAD 14
    ALOAD 15
    CHECKCAST com/hieltech/haramblur/detection/AppBlockingManager$SocialMediaStats
    GOTO L62
   L57
    ACONST_NULL
   L62
    INVOKESTATIC com/hieltech/haramblur/ui/UnifiedBlockingScreenResponsiveKt.UnifiedBlockingScreenSimple$lambda$27 (Landroidx/compose/runtime/MutableState;Lcom/hieltech/haramblur/detection/AppBlockingManager$SocialMediaStats;)V
    GOTO L35
   L34
    LINENUMBER 126 L34
    ALOAD 8
    ALOAD 1
    IFNULL L63
    ASTORE 14
    ALOAD 1
    ALOAD 17
    ALOAD 17
    ALOAD 2
    PUTFIELD com/hieltech/haramblur/ui/UnifiedBlockingScreenResponsiveKt$UnifiedBlockingScreenSimple$loadDataFunction$1.L$0 : Ljava/lang/Object;
    ALOAD 17
    ALOAD 3
    PUTFIELD com/hieltech/haramblur/ui/UnifiedBlockingScreenResponsiveKt$UnifiedBlockingScreenSimple$loadDataFunction$1.L$1 : Ljava/lang/Object;
    ALOAD 17
    ALOAD 9
    PUTFIELD com/hieltech/haramblur/ui/UnifiedBlockingScreenResponsiveKt$UnifiedBlockingScreenSimple$loadDataFunction$1.L$2 : Ljava/lang/Object;
    ALOAD 17
    ALOAD 14
    PUTFIELD com/hieltech/haramblur/ui/UnifiedBlockingScreenResponsiveKt$UnifiedBlockingScreenSimple$loadDataFunction$1.L$3 : Ljava/lang/Object;
    ALOAD 17
    ICONST_4
    PUTFIELD com/hieltech/haramblur/ui/UnifiedBlockingScreenResponsiveKt$UnifiedBlockingScreenSimple$loadDataFunction$1.label : I
    INVOKEVIRTUAL com/hieltech/haramblur/detection/EnhancedSiteBlockingManager.getCustomBlockedWebsites (Lkotlin/coroutines/Continuation;)Ljava/lang/Object;
   L8
    DUP
    ALOAD 18
    IF_ACMPNE L64
   L65
    LINENUMBER 110 L65
    ALOAD 18
    ARETURN
   L25
    ALOAD 17
    GETFIELD com/hieltech/haramblur/ui/UnifiedBlockingScreenResponsiveKt$UnifiedBlockingScreenSimple$loadDataFunction$1.L$3 : Ljava/lang/Object;
    CHECKCAST androidx/compose/runtime/MutableState
    ASTORE 14
    ALOAD 17
    GETFIELD com/hieltech/haramblur/ui/UnifiedBlockingScreenResponsiveKt$UnifiedBlockingScreenSimple$loadDataFunction$1.L$2 : Ljava/lang/Object;
    CHECKCAST androidx/compose/runtime/MutableState
    ASTORE 9
   L66
    ALOAD 17
    GETFIELD com/hieltech/haramblur/ui/UnifiedBlockingScreenResponsiveKt$UnifiedBlockingScreenSimple$loadDataFunction$1.L$1 : Ljava/lang/Object;
    CHECKCAST androidx/compose/runtime/MutableState
    ASTORE 3
   L67
    ALOAD 17
    GETFIELD com/hieltech/haramblur/ui/UnifiedBlockingScreenResponsiveKt$UnifiedBlockingScreenSimple$loadDataFunction$1.L$0 : Ljava/lang/Object;
    CHECKCAST androidx/compose/material3/SnackbarHostState
    ASTORE 2
   L9
    NOP
    ALOAD 16
    INVOKESTATIC kotlin/ResultKt.throwOnFailure (Ljava/lang/Object;)V
    ALOAD 16
   L64
    LINENUMBER 126 L64
    ASTORE 15
    ALOAD 14
    ALOAD 15
    CHECKCAST java/util/List
    ASTORE 12
    ALOAD 12
    IFNULL L63
    ALOAD 12
    GOTO L68
   L63
    INVOKESTATIC kotlin/collections/CollectionsKt.emptyList ()Ljava/util/List;
   L68
    INVOKESTATIC com/hieltech/haramblur/ui/UnifiedBlockingScreenResponsiveKt.UnifiedBlockingScreenSimple$lambda$24 (Landroidx/compose/runtime/MutableState;Ljava/util/List;)V
    GOTO L35
   L35
    LINENUMBER 129 L35
    ALOAD 9
    ICONST_1
    INVOKESTATIC com/hieltech/haramblur/ui/UnifiedBlockingScreenResponsiveKt.UnifiedBlockingScreenSimple$lambda$15 (Landroidx/compose/runtime/MutableState;Z)V
    GETSTATIC kotlin/Unit.INSTANCE : Lkotlin/Unit;
    ASTORE 11
   L10
    LINENUMBER 137 L10
    ALOAD 3
    ICONST_0
    INVOKESTATIC com/hieltech/haramblur/ui/UnifiedBlockingScreenResponsiveKt.UnifiedBlockingScreenSimple$lambda$9 (Landroidx/compose/runtime/MutableState;Z)V
   L69
    LINENUMBER 138 L69
    GOTO L70
   L2
    LINENUMBER 130 L2
    ASTORE 12
   L71
    LINENUMBER 132 L71
    ALOAD 2
   L72
    LINENUMBER 133 L72
    LDC "Failed to load data"
   L73
    LINENUMBER 132 L73
    ACONST_NULL
    ICONST_0
   L74
    LINENUMBER 134 L74
    GETSTATIC androidx/compose/material3/SnackbarDuration.Short : Landroidx/compose/material3/SnackbarDuration;
    ALOAD 17
   L75
    LINENUMBER 132 L75
    BIPUSH 6
    ACONST_NULL
    ALOAD 17
    ALOAD 3
    PUTFIELD com/hieltech/haramblur/ui/UnifiedBlockingScreenResponsiveKt$UnifiedBlockingScreenSimple$loadDataFunction$1.L$0 : Ljava/lang/Object;
    ALOAD 17
    ACONST_NULL
    PUTFIELD com/hieltech/haramblur/ui/UnifiedBlockingScreenResponsiveKt$UnifiedBlockingScreenSimple$loadDataFunction$1.L$1 : Ljava/lang/Object;
    ALOAD 17
    ACONST_NULL
    PUTFIELD com/hieltech/haramblur/ui/UnifiedBlockingScreenResponsiveKt$UnifiedBlockingScreenSimple$loadDataFunction$1.L$2 : Ljava/lang/Object;
    ALOAD 17
    ACONST_NULL
    PUTFIELD com/hieltech/haramblur/ui/UnifiedBlockingScreenResponsiveKt$UnifiedBlockingScreenSimple$loadDataFunction$1.L$3 : Ljava/lang/Object;
    ALOAD 17
    ACONST_NULL
    PUTFIELD com/hieltech/haramblur/ui/UnifiedBlockingScreenResponsiveKt$UnifiedBlockingScreenSimple$loadDataFunction$1.L$4 : Ljava/lang/Object;
    ALOAD 17
    ACONST_NULL
    PUTFIELD com/hieltech/haramblur/ui/UnifiedBlockingScreenResponsiveKt$UnifiedBlockingScreenSimple$loadDataFunction$1.L$5 : Ljava/lang/Object;
    ALOAD 17
    ACONST_NULL
    PUTFIELD com/hieltech/haramblur/ui/UnifiedBlockingScreenResponsiveKt$UnifiedBlockingScreenSimple$loadDataFunction$1.L$6 : Ljava/lang/Object;
    ALOAD 17
    ICONST_5
    PUTFIELD com/hieltech/haramblur/ui/UnifiedBlockingScreenResponsiveKt$UnifiedBlockingScreenSimple$loadDataFunction$1.label : I
    INVOKESTATIC androidx/compose/material3/SnackbarHostState.showSnackbar$default (Landroidx/compose/material3/SnackbarHostState;Ljava/lang/String;Ljava/lang/String;ZLandroidx/compose/material3/SnackbarDuration;Lkotlin/coroutines/Continuation;ILjava/lang/Object;)Ljava/lang/Object;
   L12
    DUP
    ALOAD 18
    IF_ACMPNE L76
   L77
    LINENUMBER 110 L77
    ALOAD 18
    ARETURN
   L26
    ALOAD 17
    GETFIELD com/hieltech/haramblur/ui/UnifiedBlockingScreenResponsiveKt$UnifiedBlockingScreenSimple$loadDataFunction$1.L$0 : Ljava/lang/Object;
    CHECKCAST androidx/compose/runtime/MutableState
    ASTORE 3
   L13
    NOP
    ALOAD 16
    INVOKESTATIC kotlin/ResultKt.throwOnFailure (Ljava/lang/Object;)V
    ALOAD 16
   L76
    ASTORE 11
   L14
    LINENUMBER 137 L14
    ALOAD 3
    ICONST_0
    INVOKESTATIC com/hieltech/haramblur/ui/UnifiedBlockingScreenResponsiveKt.UnifiedBlockingScreenSimple$lambda$9 (Landroidx/compose/runtime/MutableState;Z)V
   L78
    LINENUMBER 138 L78
    GOTO L70
   L11
    LINENUMBER 137 L11
    ASTORE 12
   L15
    ALOAD 3
    ICONST_0
    INVOKESTATIC com/hieltech/haramblur/ui/UnifiedBlockingScreenResponsiveKt.UnifiedBlockingScreenSimple$lambda$9 (Landroidx/compose/runtime/MutableState;Z)V
   L79
    ALOAD 12
    ATHROW
   L70
    LINENUMBER 139 L70
    GETSTATIC kotlin/Unit.INSTANCE : Lkotlin/Unit;
    ARETURN
   L27
    LINENUMBER 110 L27
    NEW java/lang/IllegalStateException
    DUP
    LDC "call to 'resume' before 'invoke' with coroutine"
    INVOKESPECIAL java/lang/IllegalStateException.<init> (Ljava/lang/String;)V
    ATHROW
   L80
    LOCALVARIABLE $appBlockingManager Lcom/hieltech/haramblur/detection/AppBlockingManager; L28 L22 0
    LOCALVARIABLE $appBlockingManager Lcom/hieltech/haramblur/detection/AppBlockingManager; L3 L23 0
    LOCALVARIABLE $appBlockingManager Lcom/hieltech/haramblur/detection/AppBlockingManager; L5 L6 0
    LOCALVARIABLE $siteBlockingManager Lcom/hieltech/haramblur/detection/EnhancedSiteBlockingManager; L28 L29 1
    LOCALVARIABLE $siteBlockingManager Lcom/hieltech/haramblur/detection/EnhancedSiteBlockingManager; L29 L33 1
    LOCALVARIABLE $siteBlockingManager Lcom/hieltech/haramblur/detection/EnhancedSiteBlockingManager; L34 L8 1
    LOCALVARIABLE snackbarHostState Landroidx/compose/material3/SnackbarHostState; L28 L22 2
    LOCALVARIABLE snackbarHostState Landroidx/compose/material3/SnackbarHostState; L44 L23 2
    LOCALVARIABLE snackbarHostState Landroidx/compose/material3/SnackbarHostState; L54 L24 2
    LOCALVARIABLE snackbarHostState Landroidx/compose/material3/SnackbarHostState; L7 L25 2
    LOCALVARIABLE snackbarHostState Landroidx/compose/material3/SnackbarHostState; L9 L10 2
    LOCALVARIABLE snackbarHostState Landroidx/compose/material3/SnackbarHostState; L2 L72 2
    LOCALVARIABLE isLoading$delegate Landroidx/compose/runtime/MutableState; L28 L22 3
    LOCALVARIABLE isLoading$delegate Landroidx/compose/runtime/MutableState; L43 L23 3
    LOCALVARIABLE isLoading$delegate Landroidx/compose/runtime/MutableState; L53 L24 3
    LOCALVARIABLE isLoading$delegate Landroidx/compose/runtime/MutableState; L61 L25 3
    LOCALVARIABLE isLoading$delegate Landroidx/compose/runtime/MutableState; L67 L69 3
    LOCALVARIABLE isLoading$delegate Landroidx/compose/runtime/MutableState; L2 L26 3
    LOCALVARIABLE isLoading$delegate Landroidx/compose/runtime/MutableState; L13 L78 3
    LOCALVARIABLE isLoading$delegate Landroidx/compose/runtime/MutableState; L11 L79 3
    LOCALVARIABLE selectedTab$delegate Landroidx/compose/runtime/MutableIntState; L28 L29 4
    LOCALVARIABLE selectedTab$delegate Landroidx/compose/runtime/MutableIntState; L29 L32 4
    LOCALVARIABLE socialMediaApps$delegate Landroidx/compose/runtime/MutableState; L28 L22 5
    LOCALVARIABLE socialMediaApps$delegate Landroidx/compose/runtime/MutableState; L42 L47 5
    LOCALVARIABLE blockedApps$delegate Landroidx/compose/runtime/MutableState; L28 L22 6
    LOCALVARIABLE blockedApps$delegate Landroidx/compose/runtime/MutableState; L41 L4 6
    LOCALVARIABLE socialMediaStats$delegate Landroidx/compose/runtime/MutableState; L28 L22 7
    LOCALVARIABLE socialMediaStats$delegate Landroidx/compose/runtime/MutableState; L40 L23 7
    LOCALVARIABLE socialMediaStats$delegate Landroidx/compose/runtime/MutableState; L52 L6 7
    LOCALVARIABLE customBlockedSites$delegate Landroidx/compose/runtime/MutableState; L28 L29 8
    LOCALVARIABLE customBlockedSites$delegate Landroidx/compose/runtime/MutableState; L29 L33 8
    LOCALVARIABLE customBlockedSites$delegate Landroidx/compose/runtime/MutableState; L34 L8 8
    LOCALVARIABLE dataLoaded$delegate Landroidx/compose/runtime/MutableState; L28 L22 9
    LOCALVARIABLE dataLoaded$delegate Landroidx/compose/runtime/MutableState; L39 L23 9
    LOCALVARIABLE dataLoaded$delegate Landroidx/compose/runtime/MutableState; L51 L24 9
    LOCALVARIABLE dataLoaded$delegate Landroidx/compose/runtime/MutableState; L60 L25 9
    LOCALVARIABLE dataLoaded$delegate Landroidx/compose/runtime/MutableState; L66 L10 9
    LOCALVARIABLE installedApps Ljava/util/List; L46 L47 12
    LOCALVARIABLE $completion Lkotlin/coroutines/Continuation; L16 L80 10
    LOCALVARIABLE $continuation Lkotlin/coroutines/Continuation; L18 L27 17
    LOCALVARIABLE $result Ljava/lang/Object; L19 L27 16
    MAXSTACK = 11
    MAXLOCALS = 19

File is unknown
The root cause java.lang.OutOfMemoryError was thrown at: unknown
	at org.jetbrains.kotlin.codegen.TransformationMethodVisitor.visitEnd(TransformationMethodVisitor.kt:89)
	at org.jetbrains.org.objectweb.asm.MethodVisitor.visitEnd(MethodVisitor.java:783)
	at org.jetbrains.kotlin.codegen.TransformationMethodVisitor.visitEnd(TransformationMethodVisitor.kt:87)
	... 54 more
Caused by: java.lang.OutOfMemoryError: GC overhead limit exceeded


