kotlin version: 2.0.21
error message: org.jetbrains.kotlin.codegen.CompilationException: Back-end (JVM) Internal error: Couldn't transform method node:
copy$default (Lcom/hieltech/haramblur/data/database/BlockingScheduleEntity;JLjava/lang/String;Ljava/lang/String;Ljava/lang/String;Ljava/lang/Integer;Ljava/lang/Integer;Ljava/lang/Integer;Ljava/lang/Integer;Ljava/lang/Integer;Ljava/lang/String;ZLjava/lang/String;JJLjava/lang/Long;Ljava/lang/Long;ILjava/lang/Object;)Lcom/hieltech/haramblur/data/database/BlockingScheduleEntity;:
   L0
    ILOAD 20
    ICONST_1
    IAND
    IFEQ L1
    ALOAD 0
    GETFIELD com/hieltech/haramblur/data/database/BlockingScheduleEntity.id : J
    LSTORE 1
   L1
    ILOAD 20
    ICONST_2
    IAND
    IFEQ L2
    ALOAD 0
    GETFIELD com/hieltech/haramblur/data/database/BlockingScheduleEntity.appPackageName : Ljava/lang/String;
    ASTORE 3
   L2
    ILOAD 20
    ICONST_4
    IAND
    IFEQ L3
    ALOAD 0
    GETFIELD com/hieltech/haramblur/data/database/BlockingScheduleEntity.siteDomain : Ljava/lang/String;
    ASTORE 4
   L3
    ILOAD 20
    BIPUSH 8
    IAND
    IFEQ L4
    ALOAD 0
    GETFIELD com/hieltech/haramblur/data/database/BlockingScheduleEntity.scheduleType : Ljava/lang/String;
    ASTORE 5
   L4
    ILOAD 20
    BIPUSH 16
    IAND
    IFEQ L5
    ALOAD 0
    GETFIELD com/hieltech/haramblur/data/database/BlockingScheduleEntity.durationMinutes : Ljava/lang/Integer;
    ASTORE 6
   L5
    ILOAD 20
    BIPUSH 32
    IAND
    IFEQ L6
    ALOAD 0
    GETFIELD com/hieltech/haramblur/data/database/BlockingScheduleEntity.startHour : Ljava/lang/Integer;
    ASTORE 7
   L6
    ILOAD 20
    BIPUSH 64
    IAND
    IFEQ L7
    ALOAD 0
    GETFIELD com/hieltech/haramblur/data/database/BlockingScheduleEntity.startMinute : Ljava/lang/Integer;
    ASTORE 8
   L7
    ILOAD 20
    SIPUSH 128
    IAND
    IFEQ L8
    ALOAD 0
    GETFIELD com/hieltech/haramblur/data/database/BlockingScheduleEntity.endHour : Ljava/lang/Integer;
    ASTORE 9
   L8
    ILOAD 20
    SIPUSH 256
    IAND
    IFEQ L9
    ALOAD 0
    GETFIELD com/hieltech/haramblur/data/database/BlockingScheduleEntity.endMinute : Ljava/lang/Integer;
    ASTORE 10
   L9
    ILOAD 20
    SIPUSH 512
    IAND
    IFEQ L10
    ALOAD 0
    GETFIELD com/hieltech/haramblur/data/database/BlockingScheduleEntity.daysOfWeek : Ljava/lang/String;
    ASTORE 11
   L10
    ILOAD 20
    SIPUSH 1024
    IAND
    IFEQ L11
    ALOAD 0
    GETFIELD com/hieltech/haramblur/data/database/BlockingScheduleEntity.isActive : Z
    ISTORE 12
   L11
    ILOAD 20
    SIPUSH 2048
    IAND
    IFEQ L12
    ALOAD 0
    GETFIELD com/hieltech/haramblur/data/database/BlockingScheduleEntity.scheduleName : Ljava/lang/String;
    ASTORE 13
   L12
    ILOAD 20
    SIPUSH 4096
    IAND
    IFEQ L13
    ALOAD 0
    GETFIELD com/hieltech/haramblur/data/database/BlockingScheduleEntity.createdAt : J
    LSTORE 14
   L13
    ILOAD 20
    SIPUSH 8192
    IAND
    IFEQ L14
    ALOAD 0
    GETFIELD com/hieltech/haramblur/data/database/BlockingScheduleEntity.updatedAt : J
    LSTORE 16
   L14
    ILOAD 20
    SIPUSH 16384
    IAND
    IFEQ L15
    ALOAD 0
    GETFIELD com/hieltech/haramblur/data/database/BlockingScheduleEntity.lastAppliedAt : Ljava/lang/Long;
    ASTORE 18
   L15
    ILOAD 20
    LDC 32768
    IAND
    IFEQ L16
    ALOAD 0
    GETFIELD com/hieltech/haramblur/data/database/BlockingScheduleEntity.nextScheduledAt : Ljava/lang/Long;
    ASTORE 19
   L16
    ALOAD 0
    LLOAD 1
    ALOAD 3
    ALOAD 4
    ALOAD 5
    ALOAD 6
    ALOAD 7
    ALOAD 8
    ALOAD 9
    ALOAD 10
    ALOAD 11
    ILOAD 12
    ALOAD 13
    LLOAD 14
    LLOAD 16
    ALOAD 18
    ALOAD 19
    INVOKEVIRTUAL com/hieltech/haramblur/data/database/BlockingScheduleEntity.copy (JLjava/lang/String;Ljava/lang/String;Ljava/lang/String;Ljava/lang/Integer;Ljava/lang/Integer;Ljava/lang/Integer;Ljava/lang/Integer;Ljava/lang/Integer;Ljava/lang/String;ZLjava/lang/String;JJLjava/lang/Long;Ljava/lang/Long;)Lcom/hieltech/haramblur/data/database/BlockingScheduleEntity;
    ARETURN
   L17
    MAXSTACK = 20
    MAXLOCALS = 22

File is unknown
The root cause java.lang.OutOfMemoryError was thrown at: unknown
	at org.jetbrains.kotlin.codegen.TransformationMethodVisitor.visitEnd(TransformationMethodVisitor.kt:89)
	at org.jetbrains.org.objectweb.asm.MethodVisitor.visitEnd(MethodVisitor.java:783)
	at org.jetbrains.org.objectweb.asm.tree.MethodNode.accept(MethodNode.java:772)
	at org.jetbrains.kotlin.backend.jvm.codegen.ClassCodegen.generateMethod(ClassCodegen.kt:453)
	at org.jetbrains.kotlin.backend.jvm.codegen.ClassCodegen.generate(ClassCodegen.kt:168)
	at org.jetbrains.kotlin.backend.jvm.FileCodegen.lower(JvmPhases.kt:39)
	at org.jetbrains.kotlin.backend.common.phaser.PhaseFactoriesKt.createFilePhase$lambda$4(PhaseFactories.kt:71)
	at org.jetbrains.kotlin.backend.common.phaser.PhaseBuildersKt$createSimpleNamedCompilerPhase$1.phaseBody(PhaseBuilders.kt:69)
	at org.jetbrains.kotlin.backend.common.phaser.SimpleNamedCompilerPhase.phaseBody(CompilerPhase.kt:226)
	at org.jetbrains.kotlin.backend.common.phaser.AbstractNamedCompilerPhase.invoke(CompilerPhase.kt:113)
	at org.jetbrains.kotlin.backend.common.phaser.PerformByIrFilePhase.invokeSequential(performByIrFile.kt:62)
	at org.jetbrains.kotlin.backend.common.phaser.PerformByIrFilePhase.invoke(performByIrFile.kt:52)
	at org.jetbrains.kotlin.backend.common.phaser.PerformByIrFilePhase.invoke(performByIrFile.kt:38)
	at org.jetbrains.kotlin.backend.common.phaser.NamedCompilerPhase.phaseBody(CompilerPhase.kt:166)
	at org.jetbrains.kotlin.backend.common.phaser.AbstractNamedCompilerPhase.invoke(CompilerPhase.kt:113)
	at org.jetbrains.kotlin.backend.common.phaser.CompositePhase.invoke(PhaseBuilders.kt:27)
	at org.jetbrains.kotlin.backend.common.phaser.CompositePhase.invoke(PhaseBuilders.kt:14)
	at org.jetbrains.kotlin.backend.common.phaser.NamedCompilerPhase.phaseBody(CompilerPhase.kt:166)
	at org.jetbrains.kotlin.backend.common.phaser.AbstractNamedCompilerPhase.invoke(CompilerPhase.kt:113)
	at org.jetbrains.kotlin.backend.common.phaser.CompilerPhaseKt.invokeToplevel(CompilerPhase.kt:62)
	at org.jetbrains.kotlin.backend.jvm.JvmIrCodegenFactory.invokeCodegen(JvmIrCodegenFactory.kt:371)
	at org.jetbrains.kotlin.codegen.CodegenFactory.generateModule(CodegenFactory.kt:47)
	at org.jetbrains.kotlin.backend.jvm.JvmIrCodegenFactory.generateModuleInFrontendIRMode(JvmIrCodegenFactory.kt:433)
	at org.jetbrains.kotlin.cli.jvm.compiler.pipeline.JvmCompilerPipelineKt.generateCodeFromIr(jvmCompilerPipeline.kt:246)
	at org.jetbrains.kotlin.cli.jvm.compiler.pipeline.JvmCompilerPipelineKt.compileModulesUsingFrontendIrAndLightTree(jvmCompilerPipeline.kt:142)
	at org.jetbrains.kotlin.cli.jvm.K2JVMCompiler.doExecute(K2JVMCompiler.kt:148)
	at org.jetbrains.kotlin.cli.jvm.K2JVMCompiler.doExecute(K2JVMCompiler.kt:43)
	at org.jetbrains.kotlin.cli.common.CLICompiler.execImpl(CLICompiler.kt:103)
	at org.jetbrains.kotlin.cli.common.CLICompiler.execImpl(CLICompiler.kt:49)
	at org.jetbrains.kotlin.cli.common.CLITool.exec(CLITool.kt:101)
	at org.jetbrains.kotlin.incremental.IncrementalJvmCompilerRunner.runCompiler(IncrementalJvmCompilerRunner.kt:464)
	at org.jetbrains.kotlin.incremental.IncrementalJvmCompilerRunner.runCompiler(IncrementalJvmCompilerRunner.kt:73)
	at org.jetbrains.kotlin.incremental.IncrementalCompilerRunner.doCompile(IncrementalCompilerRunner.kt:506)
	at org.jetbrains.kotlin.incremental.IncrementalCompilerRunner.compileImpl(IncrementalCompilerRunner.kt:423)
	at org.jetbrains.kotlin.incremental.IncrementalCompilerRunner.compileNonIncrementally(IncrementalCompilerRunner.kt:301)
	at org.jetbrains.kotlin.incremental.IncrementalCompilerRunner.compile(IncrementalCompilerRunner.kt:129)
	at org.jetbrains.kotlin.daemon.CompileServiceImplBase.execIncrementalCompiler(CompileServiceImpl.kt:675)
	at org.jetbrains.kotlin.daemon.CompileServiceImplBase.access$execIncrementalCompiler(CompileServiceImpl.kt:92)
	at org.jetbrains.kotlin.daemon.CompileServiceImpl.compile(CompileServiceImpl.kt:1660)
	at jdk.internal.reflect.GeneratedMethodAccessor91.invoke(Unknown Source)
	at java.base/jdk.internal.reflect.DelegatingMethodAccessorImpl.invoke(DelegatingMethodAccessorImpl.java:43)
	at java.base/java.lang.reflect.Method.invoke(Method.java:569)
	at java.rmi/sun.rmi.server.UnicastServerRef.dispatch(UnicastServerRef.java:360)
	at java.rmi/sun.rmi.transport.Transport$1.run(Transport.java:200)
	at java.rmi/sun.rmi.transport.Transport$1.run(Transport.java:197)
	at java.base/java.security.AccessController.doPrivileged(AccessController.java:712)
	at java.rmi/sun.rmi.transport.Transport.serviceCall(Transport.java:196)
	at java.rmi/sun.rmi.transport.tcp.TCPTransport.handleMessages(TCPTransport.java:587)
	at java.rmi/sun.rmi.transport.tcp.TCPTransport$ConnectionHandler.run0(TCPTransport.java:828)
	at java.rmi/sun.rmi.transport.tcp.TCPTransport$ConnectionHandler.lambda$run$0(TCPTransport.java:705)
	at java.base/java.security.AccessController.doPrivileged(AccessController.java:399)
	at java.rmi/sun.rmi.transport.tcp.TCPTransport$ConnectionHandler.run(TCPTransport.java:704)
	at java.base/java.util.concurrent.ThreadPoolExecutor.runWorker(ThreadPoolExecutor.java:1136)
	at java.base/java.util.concurrent.ThreadPoolExecutor$Worker.run(ThreadPoolExecutor.java:635)
	at java.base/java.lang.Thread.run(Thread.java:840)
Caused by: java.lang.OutOfMemoryError: GC overhead limit exceeded


